Compiled from "BlockHarvestUtils.java"
public class com.hypixel.hytale.server.core.modules.interaction.BlockHarvestUtils {
  static final boolean $assertionsDisabled;

  public com.hypixel.hytale.server.core.modules.interaction.BlockHarvestUtils();
    Code:
         0: aload_0
         1: invokespecial #1                  // Method java/lang/Object."<init>":()V
         4: return

  public static com.hypixel.hytale.server.core.asset.type.item.config.ItemToolSpec getSpecPowerDamageBlock(com.hypixel.hytale.server.core.asset.type.item.config.Item, com.hypixel.hytale.server.core.asset.type.blocktype.config.BlockType, com.hypixel.hytale.server.core.asset.type.item.config.ItemTool);
    Code:
         0: aload_1
         1: ifnonnull     6
         4: aconst_null
         5: areturn
         6: aload_1
         7: invokevirtual #7                  // Method com/hypixel/hytale/server/core/asset/type/blocktype/config/BlockType.getGathering:()Lcom/hypixel/hytale/server/core/asset/type/blocktype/config/BlockGathering;
        10: astore_3
        11: aload_3
        12: ifnonnull     17
        15: aconst_null
        16: areturn
        17: aload_3
        18: invokevirtual #13                 // Method com/hypixel/hytale/server/core/asset/type/blocktype/config/BlockGathering.getBreaking:()Lcom/hypixel/hytale/server/core/asset/type/blocktype/config/BlockBreakingDropType;
        21: astore        4
        23: aload         4
        25: ifnonnull     30
        28: aconst_null
        29: areturn
        30: aload         4
        32: invokevirtual #19                 // Method com/hypixel/hytale/server/core/asset/type/blocktype/config/BlockBreakingDropType.getGatherType:()Ljava/lang/String;
        35: astore        5
        37: aload         5
        39: ifnonnull     44
        42: aconst_null
        43: areturn
        44: aload_0
        45: ifnull        64
        48: aload_0
        49: invokevirtual #25                 // Method com/hypixel/hytale/server/core/asset/type/item/config/Item.getWeapon:()Lcom/hypixel/hytale/server/core/asset/type/item/config/ItemWeapon;
        52: ifnonnull     62
        55: aload_0
        56: invokevirtual #31                 // Method com/hypixel/hytale/server/core/asset/type/item/config/Item.getBuilderToolData:()Lcom/hypixel/hytale/server/core/asset/type/buildertool/config/BuilderToolData;
        59: ifnull        64
        62: aconst_null
        63: areturn
        64: aload_2
        65: ifnull        127
        68: aload_2
        69: invokevirtual #35                 // Method com/hypixel/hytale/server/core/asset/type/item/config/ItemTool.getSpecs:()[Lcom/hypixel/hytale/server/core/asset/type/item/config/ItemToolSpec;
        72: ifnull        125
        75: aload_2
        76: invokevirtual #35                 // Method com/hypixel/hytale/server/core/asset/type/item/config/ItemTool.getSpecs:()[Lcom/hypixel/hytale/server/core/asset/type/item/config/ItemToolSpec;
        79: astore        6
        81: aload         6
        83: arraylength
        84: istore        7
        86: iconst_0
        87: istore        8
        89: iload         8
        91: iload         7
        93: if_icmpge     125
        96: aload         6
        98: iload         8
       100: aaload
       101: astore        9
       103: aload         9
       105: invokevirtual #41                 // Method com/hypixel/hytale/server/core/asset/type/item/config/ItemToolSpec.getGatherType:()Ljava/lang/String;
       108: aload         5
       110: invokestatic  #44                 // Method java/util/Objects.equals:(Ljava/lang/Object;Ljava/lang/Object;)Z
       113: ifeq          119
       116: aload         9
       118: areturn
       119: iinc          8, 1
       122: goto          89
       125: aconst_null
       126: areturn
       127: invokestatic  #50                 // Method com/hypixel/hytale/server/core/asset/type/item/config/ItemToolSpec.getAssetMap:()Lcom/hypixel/hytale/assetstore/map/DefaultAssetMap;
       130: aload         5
       132: invokevirtual #54                 // Method com/hypixel/hytale/assetstore/map/DefaultAssetMap.getAsset:(Ljava/lang/Object;)Lcom/hypixel/hytale/assetstore/JsonAsset;
       135: checkcast     #42                 // class com/hypixel/hytale/server/core/asset/type/item/config/ItemToolSpec
       138: areturn

  public static double calculateDurabilityUse(com.hypixel.hytale.server.core.asset.type.item.config.Item, com.hypixel.hytale.server.core.asset.type.blocktype.config.BlockType);
    Code:
         0: aload_1
         1: ifnonnull     6
         4: dconst_0
         5: dreturn
         6: aload_1
         7: invokevirtual #7                  // Method com/hypixel/hytale/server/core/asset/type/blocktype/config/BlockType.getGathering:()Lcom/hypixel/hytale/server/core/asset/type/blocktype/config/BlockGathering;
        10: invokevirtual #60                 // Method com/hypixel/hytale/server/core/asset/type/blocktype/config/BlockGathering.isSoft:()Z
        13: ifeq          18
        16: dconst_0
        17: dreturn
        18: aload_0
        19: invokevirtual #64                 // Method com/hypixel/hytale/server/core/asset/type/item/config/Item.getTool:()Lcom/hypixel/hytale/server/core/asset/type/item/config/ItemTool;
        22: ifnonnull     27
        25: dconst_0
        26: dreturn
        27: aload_0
        28: invokevirtual #64                 // Method com/hypixel/hytale/server/core/asset/type/item/config/Item.getTool:()Lcom/hypixel/hytale/server/core/asset/type/item/config/ItemTool;
        31: astore_2
        32: aload_2
        33: invokevirtual #68                 // Method com/hypixel/hytale/server/core/asset/type/item/config/ItemTool.getDurabilityLossBlockTypes:()[Lcom/hypixel/hytale/server/core/asset/type/item/config/ItemTool$DurabilityLossBlockTypes;
        36: astore_3
        37: aload_3
        38: ifnonnull     46
        41: aload_0
        42: invokevirtual #72                 // Method com/hypixel/hytale/server/core/asset/type/item/config/Item.getDurabilityLossOnHit:()D
        45: dreturn
        46: aload_1
        47: invokevirtual #76                 // Method com/hypixel/hytale/server/core/asset/type/blocktype/config/BlockType.getId:()Ljava/lang/String;
        50: astore        4
        52: invokestatic  #79                 // Method com/hypixel/hytale/server/core/asset/type/blocktype/config/BlockType.getAssetMap:()Lcom/hypixel/hytale/assetstore/map/BlockTypeAssetMap;
        55: aload         4
        57: invokevirtual #82                 // Method com/hypixel/hytale/assetstore/map/BlockTypeAssetMap.getIndex:(Ljava/lang/Object;)I
        60: istore        5
        62: iload         5
        64: ldc           #90                 // int -2147483648
        66: if_icmpne     84
        69: new           #91                 // class java/lang/IllegalArgumentException
        72: dup
        73: aload         4
        75: invokedynamic #93,  0             // InvokeDynamic #0:makeConcatWithConstants:(Ljava/lang/String;)Ljava/lang/String;
        80: invokespecial #97                 // Method java/lang/IllegalArgumentException."<init>":(Ljava/lang/String;)V
        83: athrow
        84: invokestatic  #100                // Method com/hypixel/hytale/server/core/modules/blockset/BlockSetModule.getInstance:()Lcom/hypixel/hytale/server/core/modules/blockset/BlockSetModule;
        87: astore        6
        89: aload_3
        90: astore        7
        92: aload         7
        94: arraylength
        95: istore        8
        97: iconst_0
        98: istore        9
       100: iload         9
       102: iload         8
       104: if_icmpge     239
       107: aload         7
       109: iload         9
       111: aaload
       112: astore        10
       114: aload         10
       116: invokevirtual #106                // Method com/hypixel/hytale/server/core/asset/type/item/config/ItemTool$DurabilityLossBlockTypes.getBlockTypeIndexes:()[I
       119: astore        11
       121: aload         11
       123: ifnull        171
       126: aload         11
       128: astore        12
       130: aload         12
       132: arraylength
       133: istore        13
       135: iconst_0
       136: istore        14
       138: iload         14
       140: iload         13
       142: if_icmpge     171
       145: aload         12
       147: iload         14
       149: iaload
       150: istore        15
       152: iload         15
       154: iload         5
       156: if_icmpne     165
       159: aload         10
       161: invokevirtual #112                // Method com/hypixel/hytale/server/core/asset/type/item/config/ItemTool$DurabilityLossBlockTypes.getDurabilityLossOnHit:()D
       164: dreturn
       165: iinc          14, 1
       168: goto          138
       171: aload         10
       173: invokevirtual #113                // Method com/hypixel/hytale/server/core/asset/type/item/config/ItemTool$DurabilityLossBlockTypes.getBlockSetIndexes:()[I
       176: astore        12
       178: aload         12
       180: ifnull        233
       183: aload         12
       185: astore        13
       187: aload         13
       189: arraylength
       190: istore        14
       192: iconst_0
       193: istore        15
       195: iload         15
       197: iload         14
       199: if_icmpge     233
       202: aload         13
       204: iload         15
       206: iaload
       207: istore        16
       209: aload         6
       211: iload         16
       213: aload         4
       215: invokevirtual #116                // Method com/hypixel/hytale/server/core/modules/blockset/BlockSetModule.blockInSet:(ILjava/lang/String;)Z
       218: ifeq          227
       221: aload         10
       223: invokevirtual #112                // Method com/hypixel/hytale/server/core/asset/type/item/config/ItemTool$DurabilityLossBlockTypes.getDurabilityLossOnHit:()D
       226: dreturn
       227: iinc          15, 1
       230: goto          195
       233: iinc          9, 1
       236: goto          100
       239: aload_0
       240: invokevirtual #72                 // Method com/hypixel/hytale/server/core/asset/type/item/config/Item.getDurabilityLossOnHit:()D
       243: dreturn

  public static boolean performBlockDamage(com.hypixel.hytale.math.vector.Vector3i, com.hypixel.hytale.server.core.inventory.ItemStack, com.hypixel.hytale.server.core.asset.type.item.config.ItemTool, float, int, com.hypixel.hytale.component.Ref<com.hypixel.hytale.server.core.universe.world.storage.ChunkStore>, com.hypixel.hytale.component.CommandBuffer<com.hypixel.hytale.server.core.universe.world.storage.EntityStore>, com.hypixel.hytale.component.ComponentAccessor<com.hypixel.hytale.server.core.universe.world.storage.ChunkStore>);
    Code:
         0: aconst_null
         1: aconst_null
         2: aload_0
         3: aload_1
         4: aload_2
         5: aconst_null
         6: iconst_0
         7: fload_3
         8: iload         4
        10: aload         5
        12: aload         6
        14: aload         7
        16: invokestatic  #120                // Method performBlockDamage:(Lcom/hypixel/hytale/server/core/entity/LivingEntity;Lcom/hypixel/hytale/component/Ref;Lcom/hypixel/hytale/math/vector/Vector3i;Lcom/hypixel/hytale/server/core/inventory/ItemStack;Lcom/hypixel/hytale/server/core/asset/type/item/config/ItemTool;Ljava/lang/String;ZFILcom/hypixel/hytale/component/Ref;Lcom/hypixel/hytale/component/ComponentAccessor;Lcom/hypixel/hytale/component/ComponentAccessor;)Z
        19: ireturn

  public static boolean performBlockDamage(com.hypixel.hytale.server.core.entity.LivingEntity, com.hypixel.hytale.component.Ref<com.hypixel.hytale.server.core.universe.world.storage.EntityStore>, com.hypixel.hytale.math.vector.Vector3i, com.hypixel.hytale.server.core.inventory.ItemStack, com.hypixel.hytale.server.core.asset.type.item.config.ItemTool, java.lang.String, boolean, float, int, com.hypixel.hytale.component.Ref<com.hypixel.hytale.server.core.universe.world.storage.ChunkStore>, com.hypixel.hytale.component.ComponentAccessor<com.hypixel.hytale.server.core.universe.world.storage.EntityStore>, com.hypixel.hytale.component.ComponentAccessor<com.hypixel.hytale.server.core.universe.world.storage.ChunkStore>);
    Code:
         0: aload         10
         2: invokeinterface #126,  1          // InterfaceMethod com/hypixel/hytale/component/ComponentAccessor.getExternalData:()Ljava/lang/Object;
         7: checkcast     #132                // class com/hypixel/hytale/server/core/universe/world/storage/EntityStore
        10: invokevirtual #134                // Method com/hypixel/hytale/server/core/universe/world/storage/EntityStore.getWorld:()Lcom/hypixel/hytale/server/core/universe/world/World;
        13: astore        12
        15: aload         12
        17: invokevirtual #138                // Method com/hypixel/hytale/server/core/universe/world/World.getGameplayConfig:()Lcom/hypixel/hytale/server/core/asset/type/gameplay/GameplayConfig;
        20: astore        13
        22: aload         11
        24: aload         9
        26: invokestatic  #144                // Method com/hypixel/hytale/server/core/universe/world/chunk/WorldChunk.getComponentType:()Lcom/hypixel/hytale/component/ComponentType;
        29: invokeinterface #150,  3          // InterfaceMethod com/hypixel/hytale/component/ComponentAccessor.getComponent:(Lcom/hypixel/hytale/component/Ref;Lcom/hypixel/hytale/component/ComponentType;)Lcom/hypixel/hytale/component/Component;
        34: checkcast     #145                // class com/hypixel/hytale/server/core/universe/world/chunk/WorldChunk
        37: astore        14
        39: aload         14
        41: ifnonnull     46
        44: iconst_0
        45: ireturn
        46: aload         11
        48: aload         9
        50: invokestatic  #154                // Method com/hypixel/hytale/server/core/universe/world/chunk/BlockChunk.getComponentType:()Lcom/hypixel/hytale/component/ComponentType;
        53: invokeinterface #150,  3          // InterfaceMethod com/hypixel/hytale/component/ComponentAccessor.getComponent:(Lcom/hypixel/hytale/component/Ref;Lcom/hypixel/hytale/component/ComponentType;)Lcom/hypixel/hytale/component/Component;
        58: checkcast     #155                // class com/hypixel/hytale/server/core/universe/world/chunk/BlockChunk
        61: astore        15
        63: getstatic     #157                // Field $assertionsDisabled:Z
        66: ifne          82
        69: aload         15
        71: ifnonnull     82
        74: new           #161                // class java/lang/AssertionError
        77: dup
        78: invokespecial #163                // Method java/lang/AssertionError."<init>":()V
        81: athrow
        82: aload         15
        84: aload_2
        85: getfield      #164                // Field com/hypixel/hytale/math/vector/Vector3i.y:I
        88: invokevirtual #170                // Method com/hypixel/hytale/server/core/universe/world/chunk/BlockChunk.getSectionAtBlockY:(I)Lcom/hypixel/hytale/server/core/universe/world/chunk/section/BlockSection;
        91: astore        16
        93: aload         16
        95: aload_2
        96: getfield      #174                // Field com/hypixel/hytale/math/vector/Vector3i.x:I
        99: aload_2
       100: getfield      #164                // Field com/hypixel/hytale/math/vector/Vector3i.y:I
       103: aload_2
       104: getfield      #177                // Field com/hypixel/hytale/math/vector/Vector3i.z:I
       107: invokevirtual #180                // Method com/hypixel/hytale/server/core/universe/world/chunk/section/BlockSection.getRotationIndex:(III)I
       110: istore        17
       112: iconst_0
       113: istore        18
       115: aload         15
       117: aload_2
       118: getfield      #174                // Field com/hypixel/hytale/math/vector/Vector3i.x:I
       121: aload_2
       122: getfield      #164                // Field com/hypixel/hytale/math/vector/Vector3i.y:I
       125: aload_2
       126: getfield      #177                // Field com/hypixel/hytale/math/vector/Vector3i.z:I
       129: invokevirtual #186                // Method com/hypixel/hytale/server/core/universe/world/chunk/BlockChunk.getEnvironment:(III)I
       132: istore        19
       134: invokestatic  #189                // Method com/hypixel/hytale/server/core/asset/type/environment/config/Environment.getAssetMap:()Lcom/hypixel/hytale/assetstore/map/IndexedLookupTableAssetMap;
       137: iload         19
       139: invokevirtual #194                // Method com/hypixel/hytale/assetstore/map/IndexedLookupTableAssetMap.getAsset:(I)Lcom/hypixel/hytale/assetstore/map/JsonAssetWithMap;
       142: checkcast     #190                // class com/hypixel/hytale/server/core/asset/type/environment/config/Environment
       145: astore        20
       147: aload         10
       149: invokestatic  #199                // Method com/hypixel/hytale/server/core/modules/entity/EntityModule.get:()Lcom/hypixel/hytale/server/core/modules/entity/EntityModule;
       152: invokevirtual #205                // Method com/hypixel/hytale/server/core/modules/entity/EntityModule.getPlayerSpatialResourceType:()Lcom/hypixel/hytale/component/ResourceType;
       155: invokeinterface #209,  2          // InterfaceMethod com/hypixel/hytale/component/ComponentAccessor.getResource:(Lcom/hypixel/hytale/component/ResourceType;)Lcom/hypixel/hytale/component/Resource;
       160: checkcast     #213                // class com/hypixel/hytale/component/spatial/SpatialResource
       163: astore        21
       165: aload         20
       167: ifnull        197
       170: aload         20
       172: invokevirtual #215                // Method com/hypixel/hytale/server/core/asset/type/environment/config/Environment.isBlockModificationAllowed:()Z
       175: ifne          197
       178: aload         16
       180: aload_2
       181: getfield      #174                // Field com/hypixel/hytale/math/vector/Vector3i.x:I
       184: aload_2
       185: getfield      #164                // Field com/hypixel/hytale/math/vector/Vector3i.y:I
       188: aload_2
       189: getfield      #177                // Field com/hypixel/hytale/math/vector/Vector3i.z:I
       192: invokevirtual #218                // Method com/hypixel/hytale/server/core/universe/world/chunk/section/BlockSection.invalidateBlock:(III)V
       195: iconst_0
       196: ireturn
       197: aload         14
       199: aload_2
       200: getfield      #174                // Field com/hypixel/hytale/math/vector/Vector3i.x:I
       203: aload_2
       204: getfield      #164                // Field com/hypixel/hytale/math/vector/Vector3i.y:I
       207: aload_2
       208: getfield      #177                // Field com/hypixel/hytale/math/vector/Vector3i.z:I
       211: invokevirtual #222                // Method com/hypixel/hytale/server/core/universe/world/chunk/WorldChunk.getBlockType:(III)Lcom/hypixel/hytale/server/core/asset/type/blocktype/config/BlockType;
       214: astore        22
       216: aload         22
       218: ifnonnull     223
       221: iconst_0
       222: ireturn
       223: aload         22
       225: invokevirtual #7                  // Method com/hypixel/hytale/server/core/asset/type/blocktype/config/BlockType.getGathering:()Lcom/hypixel/hytale/server/core/asset/type/blocktype/config/BlockGathering;
       228: astore        23
       230: aload         23
       232: ifnonnull     237
       235: iconst_0
       236: ireturn
       237: iload         6
       239: ifeq          259
       242: aload         23
       244: invokevirtual #226                // Method com/hypixel/hytale/server/core/asset/type/blocktype/config/BlockGathering.getToolData:()Ljava/util/Map;
       247: aload         5
       249: invokeinterface #230,  2          // InterfaceMethod java/util/Map.containsKey:(Ljava/lang/Object;)Z
       254: ifne          259
       257: iconst_0
       258: ireturn
       259: new           #236                // class com/hypixel/hytale/math/vector/Vector3d
       262: dup
       263: invokespecial #238                // Method com/hypixel/hytale/math/vector/Vector3d."<init>":()V
       266: astore        24
       268: aload         22
       270: iload         17
       272: aload         24
       274: invokevirtual #239                // Method com/hypixel/hytale/server/core/asset/type/blocktype/config/BlockType.getBlockCenter:(ILcom/hypixel/hytale/math/vector/Vector3d;)V
       277: aload         24
       279: aload_2
       280: invokevirtual #243                // Method com/hypixel/hytale/math/vector/Vector3d.add:(Lcom/hypixel/hytale/math/vector/Vector3i;)Lcom/hypixel/hytale/math/vector/Vector3d;
       283: pop
       284: new           #165                // class com/hypixel/hytale/math/vector/Vector3i
       287: dup
       288: aload_2
       289: getfield      #174                // Field com/hypixel/hytale/math/vector/Vector3i.x:I
       292: aload_2
       293: getfield      #164                // Field com/hypixel/hytale/math/vector/Vector3i.y:I
       296: aload_2
       297: getfield      #177                // Field com/hypixel/hytale/math/vector/Vector3i.z:I
       300: invokespecial #247                // Method com/hypixel/hytale/math/vector/Vector3i."<init>":(III)V
       303: astore        25
       305: aload         22
       307: invokevirtual #249                // Method com/hypixel/hytale/server/core/asset/type/blocktype/config/BlockType.isUnknown:()Z
       310: ifne          467
       313: aload         16
       315: aload_2
       316: getfield      #174                // Field com/hypixel/hytale/math/vector/Vector3i.x:I
       319: aload_2
       320: getfield      #164                // Field com/hypixel/hytale/math/vector/Vector3i.y:I
       323: aload_2
       324: getfield      #177                // Field com/hypixel/hytale/math/vector/Vector3i.z:I
       327: invokevirtual #252                // Method com/hypixel/hytale/server/core/universe/world/chunk/section/BlockSection.getFiller:(III)I
       330: istore        26
       332: iload         26
       334: invokestatic  #255                // Method com/hypixel/hytale/server/core/util/FillerBlockUtil.unpackX:(I)I
       337: istore        27
       339: iload         26
       341: invokestatic  #261                // Method com/hypixel/hytale/server/core/util/FillerBlockUtil.unpackY:(I)I
       344: istore        28
       346: iload         26
       348: invokestatic  #264                // Method com/hypixel/hytale/server/core/util/FillerBlockUtil.unpackZ:(I)I
       351: istore        29
       353: iload         27
       355: ifne          368
       358: iload         28
       360: ifne          368
       363: iload         29
       365: ifeq          467
       368: aload         25
       370: invokevirtual #267                // Method com/hypixel/hytale/math/vector/Vector3i.clone:()Lcom/hypixel/hytale/math/vector/Vector3i;
       373: iload         27
       375: iload         28
       377: iload         29
       379: invokevirtual #271                // Method com/hypixel/hytale/math/vector/Vector3i.subtract:(III)Lcom/hypixel/hytale/math/vector/Vector3i;
       382: astore        25
       384: aload         22
       386: invokevirtual #76                 // Method com/hypixel/hytale/server/core/asset/type/blocktype/config/BlockType.getId:()Ljava/lang/String;
       389: astore        30
       391: aload         12
       393: aload         25
       395: invokevirtual #275                // Method com/hypixel/hytale/math/vector/Vector3i.getX:()I
       398: aload         25
       400: invokevirtual #279                // Method com/hypixel/hytale/math/vector/Vector3i.getY:()I
       403: aload         25
       405: invokevirtual #282                // Method com/hypixel/hytale/math/vector/Vector3i.getZ:()I
       408: invokevirtual #285                // Method com/hypixel/hytale/server/core/universe/world/World.getBlockType:(III)Lcom/hypixel/hytale/server/core/asset/type/blocktype/config/BlockType;
       411: astore        22
       413: aload         22
       415: ifnonnull     420
       418: iconst_0
       419: ireturn
       420: aload         30
       422: aload         22
       424: invokevirtual #76                 // Method com/hypixel/hytale/server/core/asset/type/blocktype/config/BlockType.getId:()Ljava/lang/String;
       427: invokevirtual #286                // Method java/lang/String.equals:(Ljava/lang/Object;)Z
       430: ifne          453
       433: aload         14
       435: aload_2
       436: getfield      #174                // Field com/hypixel/hytale/math/vector/Vector3i.x:I
       439: aload_2
       440: getfield      #164                // Field com/hypixel/hytale/math/vector/Vector3i.y:I
       443: aload_2
       444: getfield      #177                // Field com/hypixel/hytale/math/vector/Vector3i.z:I
       447: invokevirtual #290                // Method com/hypixel/hytale/server/core/universe/world/chunk/WorldChunk.breakBlock:(III)Z
       450: pop
       451: iconst_1
       452: ireturn
       453: aload         22
       455: invokevirtual #7                  // Method com/hypixel/hytale/server/core/asset/type/blocktype/config/BlockType.getGathering:()Lcom/hypixel/hytale/server/core/asset/type/blocktype/config/BlockGathering;
       458: astore        23
       460: aload         23
       462: ifnonnull     467
       465: iconst_0
       466: ireturn
       467: aload_3
       468: ifnull        478
       471: aload_3
       472: invokevirtual #294                // Method com/hypixel/hytale/server/core/inventory/ItemStack.getItem:()Lcom/hypixel/hytale/server/core/asset/type/item/config/Item;
       475: goto          479
       478: aconst_null
       479: astore        26
       481: aload         4
       483: ifnonnull     498
       486: aload         26
       488: ifnull        498
       491: aload         26
       493: invokevirtual #64                 // Method com/hypixel/hytale/server/core/asset/type/item/config/Item.getTool:()Lcom/hypixel/hytale/server/core/asset/type/item/config/ItemTool;
       496: astore        4
       498: aload         26
       500: aload         22
       502: aload         4
       504: invokestatic  #300                // Method getSpecPowerDamageBlock:(Lcom/hypixel/hytale/server/core/asset/type/item/config/Item;Lcom/hypixel/hytale/server/core/asset/type/blocktype/config/BlockType;Lcom/hypixel/hytale/server/core/asset/type/item/config/ItemTool;)Lcom/hypixel/hytale/server/core/asset/type/item/config/ItemToolSpec;
       507: astore        27
       509: aload         27
       511: ifnull        522
       514: aload         27
       516: invokevirtual #304                // Method com/hypixel/hytale/server/core/asset/type/item/config/ItemToolSpec.getPower:()F
       519: goto          523
       522: fconst_0
       523: fstore        28
       525: aload_0
       526: ifnull        543
       529: aload_0
       530: aload_1
       531: aload         10
       533: invokevirtual #308                // Method com/hypixel/hytale/server/core/entity/LivingEntity.canApplyItemStackPenalties:(Lcom/hypixel/hytale/component/Ref;Lcom/hypixel/hytale/component/ComponentAccessor;)Z
       536: ifeq          543
       539: iconst_1
       540: goto          544
       543: iconst_0
       544: istore        29
       546: fload         28
       548: fconst_0
       549: fcmpl
       550: ifeq          602
       553: aload         26
       555: ifnull        602
       558: aload         26
       560: invokevirtual #64                 // Method com/hypixel/hytale/server/core/asset/type/item/config/Item.getTool:()Lcom/hypixel/hytale/server/core/asset/type/item/config/ItemTool;
       563: ifnull        602
       566: aload_3
       567: invokevirtual #314                // Method com/hypixel/hytale/server/core/inventory/ItemStack.isBroken:()Z
       570: ifeq          602
       573: iload         29
       575: ifeq          602
       578: aload         13
       580: invokevirtual #317                // Method com/hypixel/hytale/server/core/asset/type/gameplay/GameplayConfig.getItemDurabilityConfig:()Lcom/hypixel/hytale/server/core/asset/type/gameplay/ItemDurabilityConfig;
       583: invokevirtual #323                // Method com/hypixel/hytale/server/core/asset/type/gameplay/ItemDurabilityConfig.getBrokenPenalties:()Lcom/hypixel/hytale/server/core/asset/type/gameplay/BrokenPenalties;
       586: astore        30
       588: fload         28
       590: fconst_1
       591: aload         30
       593: dconst_0
       594: invokevirtual #329                // Method com/hypixel/hytale/server/core/asset/type/gameplay/BrokenPenalties.getTool:(D)D
       597: d2f
       598: fsub
       599: fmul
       600: fstore        28
       602: iconst_1
       603: istore        31
       605: fload         28
       607: fconst_0
       608: fcmpl
       609: ifeq          647
       612: aload         23
       614: invokevirtual #13                 // Method com/hypixel/hytale/server/core/asset/type/blocktype/config/BlockGathering.getBreaking:()Lcom/hypixel/hytale/server/core/asset/type/blocktype/config/BlockBreakingDropType;
       617: astore        34
       619: fload         28
       621: fstore        30
       623: aload         34
       625: invokevirtual #334                // Method com/hypixel/hytale/server/core/asset/type/blocktype/config/BlockBreakingDropType.getQuantity:()I
       628: istore        31
       630: aload         34
       632: invokevirtual #337                // Method com/hypixel/hytale/server/core/asset/type/blocktype/config/BlockBreakingDropType.getItemId:()Ljava/lang/String;
       635: astore        32
       637: aload         34
       639: invokevirtual #340                // Method com/hypixel/hytale/server/core/asset/type/blocktype/config/BlockBreakingDropType.getDropListId:()Ljava/lang/String;
       642: astore        33
       644: goto          859
       647: aload         23
       649: invokevirtual #60                 // Method com/hypixel/hytale/server/core/asset/type/blocktype/config/BlockGathering.isSoft:()Z
       652: ifeq          708
       655: aload         23
       657: invokevirtual #343                // Method com/hypixel/hytale/server/core/asset/type/blocktype/config/BlockGathering.getSoft:()Lcom/hypixel/hytale/server/core/asset/type/blocktype/config/SoftBlockDropType;
       660: astore        34
       662: aload         34
       664: invokevirtual #347                // Method com/hypixel/hytale/server/core/asset/type/blocktype/config/SoftBlockDropType.isWeaponBreakable:()Z
       667: ifne          685
       670: aload         26
       672: ifnull        685
       675: aload         26
       677: invokevirtual #25                 // Method com/hypixel/hytale/server/core/asset/type/item/config/Item.getWeapon:()Lcom/hypixel/hytale/server/core/asset/type/item/config/ItemWeapon;
       680: ifnull        685
       683: iconst_0
       684: ireturn
       685: fconst_1
       686: fstore        30
       688: aload         34
       690: invokevirtual #352                // Method com/hypixel/hytale/server/core/asset/type/blocktype/config/SoftBlockDropType.getItemId:()Ljava/lang/String;
       693: astore        32
       695: aload         34
       697: invokevirtual #353                // Method com/hypixel/hytale/server/core/asset/type/blocktype/config/SoftBlockDropType.getDropListId:()Ljava/lang/String;
       700: astore        33
       702: fconst_1
       703: fstore        7
       705: goto          859
       708: aload         26
       710: ifnull        857
       713: aload         26
       715: invokevirtual #25                 // Method com/hypixel/hytale/server/core/asset/type/item/config/Item.getWeapon:()Lcom/hypixel/hytale/server/core/asset/type/item/config/ItemWeapon;
       718: ifnonnull     857
       721: aload_1
       722: ifnull        855
       725: aload_0
       726: ifnull        855
       729: aload         13
       731: invokevirtual #354                // Method com/hypixel/hytale/server/core/asset/type/gameplay/GameplayConfig.getGatheringConfig:()Lcom/hypixel/hytale/server/core/asset/type/gameplay/GatheringConfig;
       734: invokevirtual #358                // Method com/hypixel/hytale/server/core/asset/type/gameplay/GatheringConfig.getUnbreakableBlockConfig:()Lcom/hypixel/hytale/server/core/asset/type/gameplay/GatheringEffectsConfig;
       737: astore        34
       739: iload         8
       741: iconst_4
       742: iand
       743: ifne          791
       746: aload         34
       748: invokevirtual #366                // Method com/hypixel/hytale/server/core/asset/type/gameplay/GatheringEffectsConfig.getParticleSystemId:()Ljava/lang/String;
       751: astore        35
       753: aload         35
       755: ifnull        791
       758: invokestatic  #371                // Method com/hypixel/hytale/component/spatial/SpatialResource.getThreadLocalReferenceList:()Lit/unimi/dsi/fastutil/objects/ObjectList;
       761: astore        36
       763: aload         21
       765: invokevirtual #375                // Method com/hypixel/hytale/component/spatial/SpatialResource.getSpatialStructure:()Lcom/hypixel/hytale/component/spatial/SpatialStructure;
       768: aload         24
       770: ldc2_w        #381                // double 75.0d
       773: aload         36
       775: invokeinterface #383,  5          // InterfaceMethod com/hypixel/hytale/component/spatial/SpatialStructure.collect:(Lcom/hypixel/hytale/math/vector/Vector3d;DLjava/util/List;)V
       780: aload         35
       782: aload         24
       784: aload         36
       786: aload         10
       788: invokestatic  #389                // Method com/hypixel/hytale/server/core/universe/world/ParticleUtil.spawnParticleEffect:(Ljava/lang/String;Lcom/hypixel/hytale/math/vector/Vector3d;Ljava/util/List;Lcom/hypixel/hytale/component/ComponentAccessor;)V
       791: iload         8
       793: sipush        1024
       796: iand
       797: ifne          855
       800: aload         34
       802: invokevirtual #393                // Method com/hypixel/hytale/server/core/asset/type/gameplay/GatheringEffectsConfig.getSoundEventIndex:()I
       805: istore        35
       807: iload         35
       809: ifeq          822
       812: aload_1
       813: iload         35
       815: aload         24
       817: aload         10
       819: invokestatic  #396                // Method com/hypixel/hytale/server/core/universe/world/SoundUtil.playSoundEvent3d:(Lcom/hypixel/hytale/component/Ref;ILcom/hypixel/hytale/math/vector/Vector3d;Lcom/hypixel/hytale/component/ComponentAccessor;)V
       822: aload         26
       824: invokevirtual #64                 // Method com/hypixel/hytale/server/core/asset/type/item/config/Item.getTool:()Lcom/hypixel/hytale/server/core/asset/type/item/config/ItemTool;
       827: ifnull        855
       830: aload         26
       832: invokevirtual #64                 // Method com/hypixel/hytale/server/core/asset/type/item/config/Item.getTool:()Lcom/hypixel/hytale/server/core/asset/type/item/config/ItemTool;
       835: invokevirtual #402                // Method com/hypixel/hytale/server/core/asset/type/item/config/ItemTool.getIncorrectMaterialSoundLayerIndex:()I
       838: istore        36
       840: iload         36
       842: ifeq          855
       845: aload_1
       846: iload         36
       848: aload         24
       850: aload         10
       852: invokestatic  #396                // Method com/hypixel/hytale/server/core/universe/world/SoundUtil.playSoundEvent3d:(Lcom/hypixel/hytale/component/Ref;ILcom/hypixel/hytale/math/vector/Vector3d;Lcom/hypixel/hytale/component/ComponentAccessor;)V
       855: iconst_0
       856: ireturn
       857: iconst_0
       858: ireturn
       859: fload         30
       861: fload         7
       863: fmul
       864: fstore        30
       866: aload         11
       868: aload         9
       870: invokestatic  #405                // Method com/hypixel/hytale/server/core/universe/world/chunk/ChunkColumn.getComponentType:()Lcom/hypixel/hytale/component/ComponentType;
       873: invokeinterface #150,  3          // InterfaceMethod com/hypixel/hytale/component/ComponentAccessor.getComponent:(Lcom/hypixel/hytale/component/Ref;Lcom/hypixel/hytale/component/ComponentType;)Lcom/hypixel/hytale/component/Component;
       878: checkcast     #406                // class com/hypixel/hytale/server/core/universe/world/chunk/ChunkColumn
       881: astore        34
       883: aload         34
       885: ifnull        903
       888: aload         34
       890: aload_2
       891: getfield      #164                // Field com/hypixel/hytale/math/vector/Vector3i.y:I
       894: invokestatic  #408                // Method com/hypixel/hytale/math/util/ChunkUtil.chunkCoordinate:(I)I
       897: invokevirtual #413                // Method com/hypixel/hytale/server/core/universe/world/chunk/ChunkColumn.getSection:(I)Lcom/hypixel/hytale/component/Ref;
       900: goto          904
       903: aconst_null
       904: astore        35
       906: aload         22
       908: invokevirtual #7                  // Method com/hypixel/hytale/server/core/asset/type/blocktype/config/BlockType.getGathering:()Lcom/hypixel/hytale/server/core/asset/type/blocktype/config/BlockGathering;
       911: invokevirtual #417                // Method com/hypixel/hytale/server/core/asset/type/blocktype/config/BlockGathering.shouldUseDefaultDropWhenPlaced:()Z
       914: ifeq          986
       917: aload         35
       919: ifnull        940
       922: aload         11
       924: aload         35
       926: invokestatic  #420                // Method com/hypixel/hytale/server/core/blocktype/component/BlockPhysics.getComponentType:()Lcom/hypixel/hytale/component/ComponentType;
       929: invokeinterface #150,  3          // InterfaceMethod com/hypixel/hytale/component/ComponentAccessor.getComponent:(Lcom/hypixel/hytale/component/Ref;Lcom/hypixel/hytale/component/ComponentType;)Lcom/hypixel/hytale/component/Component;
       934: checkcast     #421                // class com/hypixel/hytale/server/core/blocktype/component/BlockPhysics
       937: goto          941
       940: aconst_null
       941: astore        36
       943: aload         36
       945: ifnull        972
       948: aload         36
       950: aload_2
       951: getfield      #174                // Field com/hypixel/hytale/math/vector/Vector3i.x:I
       954: aload_2
       955: getfield      #164                // Field com/hypixel/hytale/math/vector/Vector3i.y:I
       958: aload_2
       959: getfield      #177                // Field com/hypixel/hytale/math/vector/Vector3i.z:I
       962: invokevirtual #423                // Method com/hypixel/hytale/server/core/blocktype/component/BlockPhysics.isDeco:(III)Z
       965: ifeq          972
       968: iconst_1
       969: goto          973
       972: iconst_0
       973: istore        37
       975: iload         37
       977: ifeq          986
       980: aconst_null
       981: astore        32
       983: aconst_null
       984: astore        33
       986: aload         10
       988: invokestatic  #426                // Method com/hypixel/hytale/server/core/modules/time/TimeResource.getResourceType:()Lcom/hypixel/hytale/component/ResourceType;
       991: invokeinterface #209,  2          // InterfaceMethod com/hypixel/hytale/component/ComponentAccessor.getResource:(Lcom/hypixel/hytale/component/ResourceType;)Lcom/hypixel/hytale/component/Resource;
       996: checkcast     #427                // class com/hypixel/hytale/server/core/modules/time/TimeResource
       999: astore        36
      1001: aload         11
      1003: aload         9
      1005: invokestatic  #431                // Method com/hypixel/hytale/server/core/modules/blockhealth/BlockHealthModule.get:()Lcom/hypixel/hytale/server/core/modules/blockhealth/BlockHealthModule;
      1008: invokevirtual #436                // Method com/hypixel/hytale/server/core/modules/blockhealth/BlockHealthModule.getBlockHealthChunkComponentType:()Lcom/hypixel/hytale/component/ComponentType;
      1011: invokeinterface #150,  3          // InterfaceMethod com/hypixel/hytale/component/ComponentAccessor.getComponent:(Lcom/hypixel/hytale/component/Ref;Lcom/hypixel/hytale/component/ComponentType;)Lcom/hypixel/hytale/component/Component;
      1016: checkcast     #439                // class com/hypixel/hytale/server/core/modules/blockhealth/BlockHealthChunk
      1019: astore        37
      1021: getstatic     #157                // Field $assertionsDisabled:Z
      1024: ifne          1040
      1027: aload         37
      1029: ifnonnull     1040
      1032: new           #161                // class java/lang/AssertionError
      1035: dup
      1036: invokespecial #163                // Method java/lang/AssertionError."<init>":()V
      1039: athrow
      1040: aload         37
      1042: aload         25
      1044: invokevirtual #441                // Method com/hypixel/hytale/server/core/modules/blockhealth/BlockHealthChunk.getBlockHealth:(Lcom/hypixel/hytale/math/vector/Vector3i;)F
      1047: fstore        38
      1049: new           #445                // class com/hypixel/hytale/server/core/event/events/ecs/DamageBlockEvent
      1052: dup
      1053: aload_3
      1054: aload         25
      1056: aload         22
      1058: fload         38
      1060: fload         30
      1062: invokespecial #447                // Method com/hypixel/hytale/server/core/event/events/ecs/DamageBlockEvent."<init>":(Lcom/hypixel/hytale/server/core/inventory/ItemStack;Lcom/hypixel/hytale/math/vector/Vector3i;Lcom/hypixel/hytale/server/core/asset/type/blocktype/config/BlockType;FF)V
      1065: astore        39
      1067: aload_1
      1068: ifnull        1084
      1071: aload         10
      1073: aload_1
      1074: aload         39
      1076: invokeinterface #450,  3          // InterfaceMethod com/hypixel/hytale/component/ComponentAccessor.invoke:(Lcom/hypixel/hytale/component/Ref;Lcom/hypixel/hytale/component/system/EcsEvent;)V
      1081: goto          1093
      1084: aload         10
      1086: aload         39
      1088: invokeinterface #454,  2          // InterfaceMethod com/hypixel/hytale/component/ComponentAccessor.invoke:(Lcom/hypixel/hytale/component/system/EcsEvent;)V
      1093: aload         39
      1095: invokevirtual #457                // Method com/hypixel/hytale/server/core/event/events/ecs/DamageBlockEvent.isCancelled:()Z
      1098: ifeq          1120
      1101: aload         16
      1103: aload_2
      1104: getfield      #174                // Field com/hypixel/hytale/math/vector/Vector3i.x:I
      1107: aload_2
      1108: getfield      #164                // Field com/hypixel/hytale/math/vector/Vector3i.y:I
      1111: aload_2
      1112: getfield      #177                // Field com/hypixel/hytale/math/vector/Vector3i.z:I
      1115: invokevirtual #218                // Method com/hypixel/hytale/server/core/universe/world/chunk/section/BlockSection.invalidateBlock:(III)V
      1118: iconst_0
      1119: ireturn
      1120: aload         39
      1122: invokevirtual #460                // Method com/hypixel/hytale/server/core/event/events/ecs/DamageBlockEvent.getDamage:()F
      1125: fstore        30
      1127: aload         39
      1129: invokevirtual #463                // Method com/hypixel/hytale/server/core/event/events/ecs/DamageBlockEvent.getBlockType:()Lcom/hypixel/hytale/server/core/asset/type/blocktype/config/BlockType;
      1132: astore        22
      1134: aload         39
      1136: invokevirtual #466                // Method com/hypixel/hytale/server/core/event/events/ecs/DamageBlockEvent.getTargetBlock:()Lcom/hypixel/hytale/math/vector/Vector3i;
      1139: astore_2
      1140: aload         15
      1142: aload_2
      1143: getfield      #164                // Field com/hypixel/hytale/math/vector/Vector3i.y:I
      1146: invokevirtual #170                // Method com/hypixel/hytale/server/core/universe/world/chunk/BlockChunk.getSectionAtBlockY:(I)Lcom/hypixel/hytale/server/core/universe/world/chunk/section/BlockSection;
      1149: astore        16
      1151: aload         16
      1153: aload_2
      1154: getfield      #174                // Field com/hypixel/hytale/math/vector/Vector3i.x:I
      1157: aload_2
      1158: getfield      #164                // Field com/hypixel/hytale/math/vector/Vector3i.y:I
      1161: aload_2
      1162: getfield      #177                // Field com/hypixel/hytale/math/vector/Vector3i.z:I
      1165: invokevirtual #180                // Method com/hypixel/hytale/server/core/universe/world/chunk/section/BlockSection.getRotationIndex:(III)I
      1168: istore        17
      1170: aload         22
      1172: iload         17
      1174: aload         24
      1176: invokevirtual #239                // Method com/hypixel/hytale/server/core/asset/type/blocktype/config/BlockType.getBlockCenter:(ILcom/hypixel/hytale/math/vector/Vector3d;)V
      1179: aload         24
      1181: aload_2
      1182: invokevirtual #243                // Method com/hypixel/hytale/math/vector/Vector3d.add:(Lcom/hypixel/hytale/math/vector/Vector3i;)Lcom/hypixel/hytale/math/vector/Vector3d;
      1185: pop
      1186: aload         37
      1188: aload         36
      1190: invokevirtual #469                // Method com/hypixel/hytale/server/core/modules/time/TimeResource.getNow:()Ljava/time/Instant;
      1193: aload         12
      1195: aload_2
      1196: fload         30
      1198: invokevirtual #473                // Method com/hypixel/hytale/server/core/modules/blockhealth/BlockHealthChunk.damageBlock:(Ljava/time/Instant;Lcom/hypixel/hytale/server/core/universe/world/World;Lcom/hypixel/hytale/math/vector/Vector3i;F)Lcom/hypixel/hytale/server/core/modules/blockhealth/BlockHealth;
      1201: astore        40
      1203: aload         37
      1205: aload_2
      1206: invokevirtual #477                // Method com/hypixel/hytale/server/core/modules/blockhealth/BlockHealthChunk.isBlockFragile:(Lcom/hypixel/hytale/math/vector/Vector3i;)Z
      1209: ifne          1220
      1212: aload         40
      1214: invokevirtual #481                // Method com/hypixel/hytale/server/core/modules/blockhealth/BlockHealth.isDestroyed:()Z
      1217: ifeq          1650
      1220: aload         23
      1222: invokevirtual #226                // Method com/hypixel/hytale/server/core/asset/type/blocktype/config/BlockGathering.getToolData:()Ljava/util/Map;
      1225: aload         5
      1227: invokeinterface #486,  2          // InterfaceMethod java/util/Map.get:(Ljava/lang/Object;)Ljava/lang/Object;
      1232: checkcast     #489                // class com/hypixel/hytale/server/core/asset/type/blocktype/config/BlockGathering$BlockToolData
      1235: astore        41
      1237: aload         41
      1239: ifnull        1246
      1242: iconst_1
      1243: goto          1247
      1246: iconst_0
      1247: istore        42
      1249: iload         42
      1251: ifne          1284
      1254: aload         12
      1256: aload_2
      1257: aload         22
      1259: aload_3
      1260: iload         31
      1262: aload         32
      1264: aload         33
      1266: iload         8
      1268: aload_1
      1269: aload         9
      1271: aload         10
      1273: aload         11
      1275: invokestatic  #491                // Method performBlockBreak:(Lcom/hypixel/hytale/server/core/universe/world/World;Lcom/hypixel/hytale/math/vector/Vector3i;Lcom/hypixel/hytale/server/core/asset/type/blocktype/config/BlockType;Lcom/hypixel/hytale/server/core/inventory/ItemStack;ILjava/lang/String;Ljava/lang/String;ILcom/hypixel/hytale/component/Ref;Lcom/hypixel/hytale/component/Ref;Lcom/hypixel/hytale/component/ComponentAccessor;Lcom/hypixel/hytale/component/ComponentAccessor;)V
      1278: iconst_1
      1279: istore        18
      1281: goto          1647
      1284: aload         41
      1286: invokevirtual #495                // Method com/hypixel/hytale/server/core/asset/type/blocktype/config/BlockGathering$BlockToolData.getStateId:()Ljava/lang/String;
      1289: astore        43
      1291: aload         43
      1293: ifnull        1306
      1296: aload         22
      1298: aload         43
      1300: invokevirtual #498                // Method com/hypixel/hytale/server/core/asset/type/blocktype/config/BlockType.getBlockForState:(Ljava/lang/String;)Lcom/hypixel/hytale/server/core/asset/type/blocktype/config/BlockType;
      1303: goto          1307
      1306: aconst_null
      1307: astore        44
      1309: aload         44
      1311: ifnull        1334
      1314: aload         22
      1316: invokevirtual #76                 // Method com/hypixel/hytale/server/core/asset/type/blocktype/config/BlockType.getId:()Ljava/lang/String;
      1319: aload         44
      1321: invokevirtual #76                 // Method com/hypixel/hytale/server/core/asset/type/blocktype/config/BlockType.getId:()Ljava/lang/String;
      1324: invokevirtual #286                // Method java/lang/String.equals:(Ljava/lang/Object;)Z
      1327: ifne          1334
      1330: iconst_1
      1331: goto          1335
      1334: iconst_0
      1335: istore        45
      1337: iload         45
      1339: ifeq          1520
      1342: aload         40
      1344: fconst_1
      1345: invokevirtual #502                // Method com/hypixel/hytale/server/core/modules/blockhealth/BlockHealth.setHealth:(F)V
      1348: aload         14
      1350: aload_2
      1351: getfield      #174                // Field com/hypixel/hytale/math/vector/Vector3i.x:I
      1354: aload_2
      1355: getfield      #164                // Field com/hypixel/hytale/math/vector/Vector3i.y:I
      1358: aload_2
      1359: getfield      #177                // Field com/hypixel/hytale/math/vector/Vector3i.z:I
      1362: aload         44
      1364: invokevirtual #506                // Method com/hypixel/hytale/server/core/universe/world/chunk/WorldChunk.setBlock:(IIILcom/hypixel/hytale/server/core/asset/type/blocktype/config/BlockType;)Z
      1367: pop
      1368: iload         8
      1370: sipush        1024
      1373: iand
      1374: ifne          1431
      1377: invokestatic  #510                // Method com/hypixel/hytale/server/core/asset/type/blocksound/config/BlockSoundSet.getAssetMap:()Lcom/hypixel/hytale/assetstore/map/IndexedLookupTableAssetMap;
      1380: aload         22
      1382: invokevirtual #513                // Method com/hypixel/hytale/server/core/asset/type/blocktype/config/BlockType.getBlockSoundSetIndex:()I
      1385: invokevirtual #194                // Method com/hypixel/hytale/assetstore/map/IndexedLookupTableAssetMap.getAsset:(I)Lcom/hypixel/hytale/assetstore/map/JsonAssetWithMap;
      1388: checkcast     #511                // class com/hypixel/hytale/server/core/asset/type/blocksound/config/BlockSoundSet
      1391: astore        46
      1393: aload         46
      1395: ifnull        1431
      1398: aload         46
      1400: invokevirtual #516                // Method com/hypixel/hytale/server/core/asset/type/blocksound/config/BlockSoundSet.getSoundEventIndices:()Lit/unimi/dsi/fastutil/objects/Object2IntMap;
      1403: getstatic     #520                // Field com/hypixel/hytale/protocol/BlockSoundEvent.Break:Lcom/hypixel/hytale/protocol/BlockSoundEvent;
      1406: iconst_0
      1407: invokeinterface #528,  3          // InterfaceMethod it/unimi/dsi/fastutil/objects/Object2IntMap.getOrDefault:(Ljava/lang/Object;I)I
      1412: istore        47
      1414: iload         47
      1416: ifeq          1431
      1419: iload         47
      1421: getstatic     #534                // Field com/hypixel/hytale/protocol/SoundCategory.SFX:Lcom/hypixel/hytale/protocol/SoundCategory;
      1424: aload         24
      1426: aload         10
      1428: invokestatic  #540                // Method com/hypixel/hytale/server/core/universe/world/SoundUtil.playSoundEvent3d:(ILcom/hypixel/hytale/protocol/SoundCategory;Lcom/hypixel/hytale/math/vector/Vector3d;Lcom/hypixel/hytale/component/ComponentAccessor;)V
      1431: iload         8
      1433: sipush        2048
      1436: iand
      1437: ifne          1647
      1440: aload         22
      1442: iconst_1
      1443: aload         41
      1445: invokevirtual #543                // Method com/hypixel/hytale/server/core/asset/type/blocktype/config/BlockGathering$BlockToolData.getItemId:()Ljava/lang/String;
      1448: aload         41
      1450: invokevirtual #544                // Method com/hypixel/hytale/server/core/asset/type/blocktype/config/BlockGathering$BlockToolData.getDropListId:()Ljava/lang/String;
      1453: invokestatic  #545                // Method getDrops:(Lcom/hypixel/hytale/server/core/asset/type/blocktype/config/BlockType;ILjava/lang/String;Ljava/lang/String;)Ljava/util/List;
      1456: astore        46
      1458: new           #236                // class com/hypixel/hytale/math/vector/Vector3d
      1461: dup
      1462: aload_2
      1463: getfield      #174                // Field com/hypixel/hytale/math/vector/Vector3i.x:I
      1466: i2d
      1467: ldc2_w        #549                // double 0.5d
      1470: dadd
      1471: aload_2
      1472: getfield      #164                // Field com/hypixel/hytale/math/vector/Vector3i.y:I
      1475: i2d
      1476: aload_2
      1477: getfield      #177                // Field com/hypixel/hytale/math/vector/Vector3i.z:I
      1480: i2d
      1481: ldc2_w        #549                // double 0.5d
      1484: dadd
      1485: invokespecial #551                // Method com/hypixel/hytale/math/vector/Vector3d."<init>":(DDD)V
      1488: astore        47
      1490: aload         10
      1492: aload         46
      1494: aload         47
      1496: getstatic     #554                // Field com/hypixel/hytale/math/vector/Vector3f.ZERO:Lcom/hypixel/hytale/math/vector/Vector3f;
      1499: invokestatic  #560                // Method com/hypixel/hytale/server/core/modules/entity/item/ItemComponent.generateItemDrops:(Lcom/hypixel/hytale/component/ComponentAccessor;Ljava/util/List;Lcom/hypixel/hytale/math/vector/Vector3d;Lcom/hypixel/hytale/math/vector/Vector3f;)[Lcom/hypixel/hytale/component/Holder;
      1502: astore        48
      1504: aload         10
      1506: aload         48
      1508: getstatic     #566                // Field com/hypixel/hytale/component/AddReason.SPAWN:Lcom/hypixel/hytale/component/AddReason;
      1511: invokeinterface #572,  3          // InterfaceMethod com/hypixel/hytale/component/ComponentAccessor.addEntities:([Lcom/hypixel/hytale/component/Holder;Lcom/hypixel/hytale/component/AddReason;)[Lcom/hypixel/hytale/component/Ref;
      1516: pop
      1517: goto          1647
      1520: aload         12
      1522: aload_2
      1523: aload         22
      1525: aload_3
      1526: iload         31
      1528: aload         32
      1530: aload         33
      1532: iload         8
      1534: sipush        2048
      1537: ior
      1538: aload_1
      1539: aload         9
      1541: aload         10
      1543: aload         11
      1545: invokestatic  #491                // Method performBlockBreak:(Lcom/hypixel/hytale/server/core/universe/world/World;Lcom/hypixel/hytale/math/vector/Vector3i;Lcom/hypixel/hytale/server/core/asset/type/blocktype/config/BlockType;Lcom/hypixel/hytale/server/core/inventory/ItemStack;ILjava/lang/String;Ljava/lang/String;ILcom/hypixel/hytale/component/Ref;Lcom/hypixel/hytale/component/Ref;Lcom/hypixel/hytale/component/ComponentAccessor;Lcom/hypixel/hytale/component/ComponentAccessor;)V
      1548: iconst_1
      1549: istore        18
      1551: iload         8
      1553: sipush        2048
      1556: iand
      1557: ifne          1647
      1560: aload         22
      1562: iconst_1
      1563: aload         41
      1565: invokevirtual #543                // Method com/hypixel/hytale/server/core/asset/type/blocktype/config/BlockGathering$BlockToolData.getItemId:()Ljava/lang/String;
      1568: aload         41
      1570: invokevirtual #544                // Method com/hypixel/hytale/server/core/asset/type/blocktype/config/BlockGathering$BlockToolData.getDropListId:()Ljava/lang/String;
      1573: invokestatic  #545                // Method getDrops:(Lcom/hypixel/hytale/server/core/asset/type/blocktype/config/BlockType;ILjava/lang/String;Ljava/lang/String;)Ljava/util/List;
      1576: astore        46
      1578: aload         46
      1580: invokeinterface #576,  1          // InterfaceMethod java/util/List.isEmpty:()Z
      1585: ifne          1647
      1588: new           #236                // class com/hypixel/hytale/math/vector/Vector3d
      1591: dup
      1592: aload_2
      1593: getfield      #174                // Field com/hypixel/hytale/math/vector/Vector3i.x:I
      1596: i2d
      1597: ldc2_w        #549                // double 0.5d
      1600: dadd
      1601: aload_2
      1602: getfield      #164                // Field com/hypixel/hytale/math/vector/Vector3i.y:I
      1605: i2d
      1606: aload_2
      1607: getfield      #177                // Field com/hypixel/hytale/math/vector/Vector3i.z:I
      1610: i2d
      1611: ldc2_w        #549                // double 0.5d
      1614: dadd
      1615: invokespecial #551                // Method com/hypixel/hytale/math/vector/Vector3d."<init>":(DDD)V
      1618: astore        47
      1620: aload         10
      1622: aload         46
      1624: aload         47
      1626: getstatic     #554                // Field com/hypixel/hytale/math/vector/Vector3f.ZERO:Lcom/hypixel/hytale/math/vector/Vector3f;
      1629: invokestatic  #560                // Method com/hypixel/hytale/server/core/modules/entity/item/ItemComponent.generateItemDrops:(Lcom/hypixel/hytale/component/ComponentAccessor;Ljava/util/List;Lcom/hypixel/hytale/math/vector/Vector3d;Lcom/hypixel/hytale/math/vector/Vector3f;)[Lcom/hypixel/hytale/component/Holder;
      1632: astore        48
      1634: aload         10
      1636: aload         48
      1638: getstatic     #566                // Field com/hypixel/hytale/component/AddReason.SPAWN:Lcom/hypixel/hytale/component/AddReason;
      1641: invokeinterface #572,  3          // InterfaceMethod com/hypixel/hytale/component/ComponentAccessor.addEntities:([Lcom/hypixel/hytale/component/Holder;Lcom/hypixel/hytale/component/AddReason;)[Lcom/hypixel/hytale/component/Ref;
      1646: pop
      1647: goto          1713
      1650: iload         8
      1652: sipush        1024
      1655: iand
      1656: ifne          1713
      1659: invokestatic  #510                // Method com/hypixel/hytale/server/core/asset/type/blocksound/config/BlockSoundSet.getAssetMap:()Lcom/hypixel/hytale/assetstore/map/IndexedLookupTableAssetMap;
      1662: aload         22
      1664: invokevirtual #513                // Method com/hypixel/hytale/server/core/asset/type/blocktype/config/BlockType.getBlockSoundSetIndex:()I
      1667: invokevirtual #194                // Method com/hypixel/hytale/assetstore/map/IndexedLookupTableAssetMap.getAsset:(I)Lcom/hypixel/hytale/assetstore/map/JsonAssetWithMap;
      1670: checkcast     #511                // class com/hypixel/hytale/server/core/asset/type/blocksound/config/BlockSoundSet
      1673: astore        41
      1675: aload         41
      1677: ifnull        1713
      1680: aload         41
      1682: invokevirtual #516                // Method com/hypixel/hytale/server/core/asset/type/blocksound/config/BlockSoundSet.getSoundEventIndices:()Lit/unimi/dsi/fastutil/objects/Object2IntMap;
      1685: getstatic     #581                // Field com/hypixel/hytale/protocol/BlockSoundEvent.Hit:Lcom/hypixel/hytale/protocol/BlockSoundEvent;
      1688: iconst_0
      1689: invokeinterface #528,  3          // InterfaceMethod it/unimi/dsi/fastutil/objects/Object2IntMap.getOrDefault:(Ljava/lang/Object;I)I
      1694: istore        42
      1696: iload         42
      1698: ifeq          1713
      1701: iload         42
      1703: getstatic     #534                // Field com/hypixel/hytale/protocol/SoundCategory.SFX:Lcom/hypixel/hytale/protocol/SoundCategory;
      1706: aload         24
      1708: aload         10
      1710: invokestatic  #540                // Method com/hypixel/hytale/server/core/universe/world/SoundUtil.playSoundEvent3d:(ILcom/hypixel/hytale/protocol/SoundCategory;Lcom/hypixel/hytale/math/vector/Vector3d;Lcom/hypixel/hytale/component/ComponentAccessor;)V
      1713: aload_1
      1714: ifnull        1923
      1717: aload_0
      1718: ifnull        1923
      1721: iload         8
      1723: sipush        1024
      1726: iand
      1727: ifne          1812
      1730: aload         24
      1732: getstatic     #584                // Field com/hypixel/hytale/math/vector/Vector3d.MAX:Lcom/hypixel/hytale/math/vector/Vector3d;
      1735: invokevirtual #588                // Method com/hypixel/hytale/math/vector/Vector3d.equals:(Lcom/hypixel/hytale/math/vector/Vector3d;)Z
      1738: ifne          1812
      1741: iconst_0
      1742: istore        41
      1744: aload         27
      1746: ifnull        1756
      1749: aload         27
      1751: invokevirtual #591                // Method com/hypixel/hytale/server/core/asset/type/item/config/ItemToolSpec.getHitSoundLayerIndex:()I
      1754: istore        41
      1756: iload         41
      1758: ifne          1784
      1761: aload         26
      1763: ifnull        1784
      1766: aload         26
      1768: invokevirtual #64                 // Method com/hypixel/hytale/server/core/asset/type/item/config/Item.getTool:()Lcom/hypixel/hytale/server/core/asset/type/item/config/ItemTool;
      1771: ifnull        1784
      1774: aload         26
      1776: invokevirtual #64                 // Method com/hypixel/hytale/server/core/asset/type/item/config/Item.getTool:()Lcom/hypixel/hytale/server/core/asset/type/item/config/ItemTool;
      1779: invokevirtual #594                // Method com/hypixel/hytale/server/core/asset/type/item/config/ItemTool.getHitSoundLayerIndex:()I
      1782: istore        41
      1784: iload         41
      1786: ifeq          1812
      1789: aload_1
      1790: iload         41
      1792: aload         24
      1794: invokevirtual #595                // Method com/hypixel/hytale/math/vector/Vector3d.getX:()D
      1797: aload         24
      1799: invokevirtual #597                // Method com/hypixel/hytale/math/vector/Vector3d.getY:()D
      1802: aload         24
      1804: invokevirtual #599                // Method com/hypixel/hytale/math/vector/Vector3d.getZ:()D
      1807: aload         10
      1809: invokestatic  #601                // Method com/hypixel/hytale/server/core/universe/world/SoundUtil.playSoundEvent3d:(Lcom/hypixel/hytale/component/Ref;IDDDLcom/hypixel/hytale/component/ComponentAccessor;)V
      1812: aload         27
      1814: ifnull        1923
      1817: aload         27
      1819: invokevirtual #604                // Method com/hypixel/hytale/server/core/asset/type/item/config/ItemToolSpec.isIncorrect:()Z
      1822: ifeq          1923
      1825: aload         13
      1827: invokevirtual #354                // Method com/hypixel/hytale/server/core/asset/type/gameplay/GameplayConfig.getGatheringConfig:()Lcom/hypixel/hytale/server/core/asset/type/gameplay/GatheringConfig;
      1830: invokevirtual #607                // Method com/hypixel/hytale/server/core/asset/type/gameplay/GatheringConfig.getIncorrectToolConfig:()Lcom/hypixel/hytale/server/core/asset/type/gameplay/GatheringEffectsConfig;
      1833: astore        41
      1835: aload         41
      1837: ifnull        1923
      1840: iload         8
      1842: iconst_4
      1843: iand
      1844: ifne          1892
      1847: aload         41
      1849: invokevirtual #366                // Method com/hypixel/hytale/server/core/asset/type/gameplay/GatheringEffectsConfig.getParticleSystemId:()Ljava/lang/String;
      1852: astore        42
      1854: aload         42
      1856: ifnull        1892
      1859: invokestatic  #371                // Method com/hypixel/hytale/component/spatial/SpatialResource.getThreadLocalReferenceList:()Lit/unimi/dsi/fastutil/objects/ObjectList;
      1862: astore        43
      1864: aload         21
      1866: invokevirtual #375                // Method com/hypixel/hytale/component/spatial/SpatialResource.getSpatialStructure:()Lcom/hypixel/hytale/component/spatial/SpatialStructure;
      1869: aload         24
      1871: ldc2_w        #381                // double 75.0d
      1874: aload         43
      1876: invokeinterface #383,  5          // InterfaceMethod com/hypixel/hytale/component/spatial/SpatialStructure.collect:(Lcom/hypixel/hytale/math/vector/Vector3d;DLjava/util/List;)V
      1881: aload         42
      1883: aload         24
      1885: aload         43
      1887: aload         10
      1889: invokestatic  #389                // Method com/hypixel/hytale/server/core/universe/world/ParticleUtil.spawnParticleEffect:(Ljava/lang/String;Lcom/hypixel/hytale/math/vector/Vector3d;Ljava/util/List;Lcom/hypixel/hytale/component/ComponentAccessor;)V
      1892: iload         8
      1894: sipush        1024
      1897: iand
      1898: ifne          1923
      1901: aload         41
      1903: invokevirtual #393                // Method com/hypixel/hytale/server/core/asset/type/gameplay/GatheringEffectsConfig.getSoundEventIndex:()I
      1906: istore        42
      1908: iload         42
      1910: ifeq          1923
      1913: aload_1
      1914: iload         42
      1916: aload         24
      1918: aload         10
      1920: invokestatic  #396                // Method com/hypixel/hytale/server/core/universe/world/SoundUtil.playSoundEvent3d:(Lcom/hypixel/hytale/component/Ref;ILcom/hypixel/hytale/math/vector/Vector3d;Lcom/hypixel/hytale/component/ComponentAccessor;)V
      1923: aload_0
      1924: ifnull        2001
      1927: aload_1
      1928: ifnull        2001
      1931: aload_0
      1932: aload_1
      1933: aload         10
      1935: invokevirtual #610                // Method com/hypixel/hytale/server/core/entity/LivingEntity.canDecreaseItemStackDurability:(Lcom/hypixel/hytale/component/Ref;Lcom/hypixel/hytale/component/ComponentAccessor;)Z
      1938: ifeq          2001
      1941: aload_3
      1942: ifnull        2001
      1945: aload_3
      1946: invokevirtual #613                // Method com/hypixel/hytale/server/core/inventory/ItemStack.isUnbreakable:()Z
      1949: ifne          2001
      1952: aload_0
      1953: invokevirtual #616                // Method com/hypixel/hytale/server/core/entity/LivingEntity.getInventory:()Lcom/hypixel/hytale/server/core/inventory/Inventory;
      1956: invokevirtual #620                // Method com/hypixel/hytale/server/core/inventory/Inventory.getActiveHotbarSlot:()B
      1959: istore        41
      1961: iload         41
      1963: iconst_m1
      1964: if_icmpeq     2001
      1967: aload         26
      1969: aload         22
      1971: invokestatic  #626                // Method calculateDurabilityUse:(Lcom/hypixel/hytale/server/core/asset/type/item/config/Item;Lcom/hypixel/hytale/server/core/asset/type/blocktype/config/BlockType;)D
      1974: dstore        42
      1976: aload_0
      1977: invokevirtual #616                // Method com/hypixel/hytale/server/core/entity/LivingEntity.getInventory:()Lcom/hypixel/hytale/server/core/inventory/Inventory;
      1980: invokevirtual #630                // Method com/hypixel/hytale/server/core/inventory/Inventory.getHotbar:()Lcom/hypixel/hytale/server/core/inventory/container/ItemContainer;
      1983: astore        44
      1985: aload_0
      1986: aload_1
      1987: aload_3
      1988: aload         44
      1990: iload         41
      1992: dload         42
      1994: dneg
      1995: aload         10
      1997: invokevirtual #634                // Method com/hypixel/hytale/server/core/entity/LivingEntity.updateItemStackDurability:(Lcom/hypixel/hytale/component/Ref;Lcom/hypixel/hytale/server/core/inventory/ItemStack;Lcom/hypixel/hytale/server/core/inventory/container/ItemContainer;IDLcom/hypixel/hytale/component/ComponentAccessor;)Lcom/hypixel/hytale/server/core/inventory/transaction/ItemStackSlotTransaction;
      2000: pop
      2001: iload         18
      2003: ireturn

  public static void performBlockBreak(com.hypixel.hytale.component.Ref<com.hypixel.hytale.server.core.universe.world.storage.EntityStore>, com.hypixel.hytale.server.core.inventory.ItemStack, com.hypixel.hytale.math.vector.Vector3i, com.hypixel.hytale.component.Ref<com.hypixel.hytale.server.core.universe.world.storage.ChunkStore>, com.hypixel.hytale.component.ComponentAccessor<com.hypixel.hytale.server.core.universe.world.storage.EntityStore>, com.hypixel.hytale.component.ComponentAccessor<com.hypixel.hytale.server.core.universe.world.storage.ChunkStore>);
    Code:
         0: aload_0
         1: aload_1
         2: aload_2
         3: iconst_0
         4: aload_3
         5: aload         4
         7: aload         5
         9: invokestatic  #638                // Method performBlockBreak:(Lcom/hypixel/hytale/component/Ref;Lcom/hypixel/hytale/server/core/inventory/ItemStack;Lcom/hypixel/hytale/math/vector/Vector3i;ILcom/hypixel/hytale/component/Ref;Lcom/hypixel/hytale/component/ComponentAccessor;Lcom/hypixel/hytale/component/ComponentAccessor;)V
        12: return

  public static void performBlockBreak(com.hypixel.hytale.component.Ref<com.hypixel.hytale.server.core.universe.world.storage.EntityStore>, com.hypixel.hytale.server.core.inventory.ItemStack, com.hypixel.hytale.math.vector.Vector3i, int, com.hypixel.hytale.component.Ref<com.hypixel.hytale.server.core.universe.world.storage.ChunkStore>, com.hypixel.hytale.component.ComponentAccessor<com.hypixel.hytale.server.core.universe.world.storage.EntityStore>, com.hypixel.hytale.component.ComponentAccessor<com.hypixel.hytale.server.core.universe.world.storage.ChunkStore>);
    Code:
         0: aload         6
         2: invokeinterface #126,  1          // InterfaceMethod com/hypixel/hytale/component/ComponentAccessor.getExternalData:()Ljava/lang/Object;
         7: checkcast     #641                // class com/hypixel/hytale/server/core/universe/world/storage/ChunkStore
        10: invokevirtual #643                // Method com/hypixel/hytale/server/core/universe/world/storage/ChunkStore.getWorld:()Lcom/hypixel/hytale/server/core/universe/world/World;
        13: astore        7
        15: aload_2
        16: invokevirtual #275                // Method com/hypixel/hytale/math/vector/Vector3i.getX:()I
        19: istore        8
        21: aload_2
        22: invokevirtual #279                // Method com/hypixel/hytale/math/vector/Vector3i.getY:()I
        25: istore        9
        27: aload_2
        28: invokevirtual #282                // Method com/hypixel/hytale/math/vector/Vector3i.getZ:()I
        31: istore        10
        33: aload         6
        35: aload         4
        37: invokestatic  #144                // Method com/hypixel/hytale/server/core/universe/world/chunk/WorldChunk.getComponentType:()Lcom/hypixel/hytale/component/ComponentType;
        40: invokeinterface #150,  3          // InterfaceMethod com/hypixel/hytale/component/ComponentAccessor.getComponent:(Lcom/hypixel/hytale/component/Ref;Lcom/hypixel/hytale/component/ComponentType;)Lcom/hypixel/hytale/component/Component;
        45: checkcast     #145                // class com/hypixel/hytale/server/core/universe/world/chunk/WorldChunk
        48: astore        11
        50: getstatic     #157                // Field $assertionsDisabled:Z
        53: ifne          69
        56: aload         11
        58: ifnonnull     69
        61: new           #161                // class java/lang/AssertionError
        64: dup
        65: invokespecial #163                // Method java/lang/AssertionError."<init>":()V
        68: athrow
        69: aload         11
        71: iload         8
        73: iload         9
        75: iload         10
        77: invokevirtual #644                // Method com/hypixel/hytale/server/core/universe/world/chunk/WorldChunk.getBlock:(III)I
        80: istore        12
        82: invokestatic  #79                 // Method com/hypixel/hytale/server/core/asset/type/blocktype/config/BlockType.getAssetMap:()Lcom/hypixel/hytale/assetstore/map/BlockTypeAssetMap;
        85: iload         12
        87: invokevirtual #647                // Method com/hypixel/hytale/assetstore/map/BlockTypeAssetMap.getAsset:(I)Lcom/hypixel/hytale/assetstore/map/JsonAssetWithMap;
        90: checkcast     #8                  // class com/hypixel/hytale/server/core/asset/type/blocktype/config/BlockType
        93: astore        13
        95: aload         13
        97: ifnonnull     101
       100: return
       101: aload_2
       102: astore        14
       104: aload         13
       106: invokevirtual #249                // Method com/hypixel/hytale/server/core/asset/type/blocktype/config/BlockType.isUnknown:()Z
       109: ifne          266
       112: aload         6
       114: aload         4
       116: invokestatic  #154                // Method com/hypixel/hytale/server/core/universe/world/chunk/BlockChunk.getComponentType:()Lcom/hypixel/hytale/component/ComponentType;
       119: invokeinterface #150,  3          // InterfaceMethod com/hypixel/hytale/component/ComponentAccessor.getComponent:(Lcom/hypixel/hytale/component/Ref;Lcom/hypixel/hytale/component/ComponentType;)Lcom/hypixel/hytale/component/Component;
       124: checkcast     #155                // class com/hypixel/hytale/server/core/universe/world/chunk/BlockChunk
       127: astore        15
       129: getstatic     #157                // Field $assertionsDisabled:Z
       132: ifne          148
       135: aload         15
       137: ifnonnull     148
       140: new           #161                // class java/lang/AssertionError
       143: dup
       144: invokespecial #163                // Method java/lang/AssertionError."<init>":()V
       147: athrow
       148: aload         15
       150: iload         9
       152: invokevirtual #170                // Method com/hypixel/hytale/server/core/universe/world/chunk/BlockChunk.getSectionAtBlockY:(I)Lcom/hypixel/hytale/server/core/universe/world/chunk/section/BlockSection;
       155: astore        16
       157: aload         16
       159: iload         8
       161: iload         9
       163: iload         10
       165: invokevirtual #252                // Method com/hypixel/hytale/server/core/universe/world/chunk/section/BlockSection.getFiller:(III)I
       168: istore        17
       170: iload         17
       172: invokestatic  #255                // Method com/hypixel/hytale/server/core/util/FillerBlockUtil.unpackX:(I)I
       175: istore        18
       177: iload         17
       179: invokestatic  #261                // Method com/hypixel/hytale/server/core/util/FillerBlockUtil.unpackY:(I)I
       182: istore        19
       184: iload         17
       186: invokestatic  #264                // Method com/hypixel/hytale/server/core/util/FillerBlockUtil.unpackZ:(I)I
       189: istore        20
       191: iload         18
       193: ifne          206
       196: iload         19
       198: ifne          206
       201: iload         20
       203: ifeq          266
       206: aload         14
       208: invokevirtual #267                // Method com/hypixel/hytale/math/vector/Vector3i.clone:()Lcom/hypixel/hytale/math/vector/Vector3i;
       211: iload         18
       213: iload         19
       215: iload         20
       217: invokevirtual #271                // Method com/hypixel/hytale/math/vector/Vector3i.subtract:(III)Lcom/hypixel/hytale/math/vector/Vector3i;
       220: astore        14
       222: aload         7
       224: aload         14
       226: invokevirtual #648                // Method com/hypixel/hytale/server/core/universe/world/World.getBlockType:(Lcom/hypixel/hytale/math/vector/Vector3i;)Lcom/hypixel/hytale/server/core/asset/type/blocktype/config/BlockType;
       229: astore        21
       231: aload         21
       233: ifnull        266
       236: aload         13
       238: invokevirtual #76                 // Method com/hypixel/hytale/server/core/asset/type/blocktype/config/BlockType.getId:()Ljava/lang/String;
       241: aload         21
       243: invokevirtual #76                 // Method com/hypixel/hytale/server/core/asset/type/blocktype/config/BlockType.getId:()Ljava/lang/String;
       246: invokevirtual #286                // Method java/lang/String.equals:(Ljava/lang/Object;)Z
       249: ifne          266
       252: aload         7
       254: iload         8
       256: iload         9
       258: iload         10
       260: iload_3
       261: invokevirtual #651                // Method com/hypixel/hytale/server/core/universe/world/World.breakBlock:(IIII)Z
       264: pop
       265: return
       266: aload         7
       268: aload         14
       270: aload         13
       272: aload_1
       273: iconst_0
       274: aconst_null
       275: aconst_null
       276: iload_3
       277: aload_0
       278: aload         4
       280: aload         5
       282: aload         6
       284: invokestatic  #491                // Method performBlockBreak:(Lcom/hypixel/hytale/server/core/universe/world/World;Lcom/hypixel/hytale/math/vector/Vector3i;Lcom/hypixel/hytale/server/core/asset/type/blocktype/config/BlockType;Lcom/hypixel/hytale/server/core/inventory/ItemStack;ILjava/lang/String;Ljava/lang/String;ILcom/hypixel/hytale/component/Ref;Lcom/hypixel/hytale/component/Ref;Lcom/hypixel/hytale/component/ComponentAccessor;Lcom/hypixel/hytale/component/ComponentAccessor;)V
       287: return

  public static void performBlockBreak(com.hypixel.hytale.server.core.universe.world.World, com.hypixel.hytale.math.vector.Vector3i, com.hypixel.hytale.server.core.asset.type.blocktype.config.BlockType, com.hypixel.hytale.server.core.inventory.ItemStack, int, java.lang.String, java.lang.String, int, com.hypixel.hytale.component.Ref<com.hypixel.hytale.server.core.universe.world.storage.EntityStore>, com.hypixel.hytale.component.Ref<com.hypixel.hytale.server.core.universe.world.storage.ChunkStore>, com.hypixel.hytale.component.ComponentAccessor<com.hypixel.hytale.server.core.universe.world.storage.EntityStore>, com.hypixel.hytale.component.ComponentAccessor<com.hypixel.hytale.server.core.universe.world.storage.ChunkStore>);
    Code:
         0: aload_0
         1: astore        12
         3: aload_1
         4: astore        13
         6: aload         9
         8: astore        14
        10: aload         11
        12: astore        15
        14: aload         8
        16: ifnull        183
        19: new           #654                // class com/hypixel/hytale/server/core/event/events/ecs/BreakBlockEvent
        22: dup
        23: aload_3
        24: aload         13
        26: aload_2
        27: invokespecial #656                // Method com/hypixel/hytale/server/core/event/events/ecs/BreakBlockEvent."<init>":(Lcom/hypixel/hytale/server/core/inventory/ItemStack;Lcom/hypixel/hytale/math/vector/Vector3i;Lcom/hypixel/hytale/server/core/asset/type/blocktype/config/BlockType;)V
        30: astore        16
        32: aload         10
        34: aload         8
        36: aload         16
        38: invokeinterface #450,  3          // InterfaceMethod com/hypixel/hytale/component/ComponentAccessor.invoke:(Lcom/hypixel/hytale/component/Ref;Lcom/hypixel/hytale/component/system/EcsEvent;)V
        43: aload         16
        45: invokevirtual #659                // Method com/hypixel/hytale/server/core/event/events/ecs/BreakBlockEvent.isCancelled:()Z
        48: ifeq          120
        51: aload         11
        53: aload         14
        55: invokestatic  #154                // Method com/hypixel/hytale/server/core/universe/world/chunk/BlockChunk.getComponentType:()Lcom/hypixel/hytale/component/ComponentType;
        58: invokeinterface #150,  3          // InterfaceMethod com/hypixel/hytale/component/ComponentAccessor.getComponent:(Lcom/hypixel/hytale/component/Ref;Lcom/hypixel/hytale/component/ComponentType;)Lcom/hypixel/hytale/component/Component;
        63: checkcast     #155                // class com/hypixel/hytale/server/core/universe/world/chunk/BlockChunk
        66: astore        17
        68: getstatic     #157                // Field $assertionsDisabled:Z
        71: ifne          87
        74: aload         17
        76: ifnonnull     87
        79: new           #161                // class java/lang/AssertionError
        82: dup
        83: invokespecial #163                // Method java/lang/AssertionError."<init>":()V
        86: athrow
        87: aload         17
        89: aload         13
        91: invokevirtual #279                // Method com/hypixel/hytale/math/vector/Vector3i.getY:()I
        94: invokevirtual #170                // Method com/hypixel/hytale/server/core/universe/world/chunk/BlockChunk.getSectionAtBlockY:(I)Lcom/hypixel/hytale/server/core/universe/world/chunk/section/BlockSection;
        97: astore        18
        99: aload         18
       101: aload         13
       103: invokevirtual #275                // Method com/hypixel/hytale/math/vector/Vector3i.getX:()I
       106: aload         13
       108: invokevirtual #279                // Method com/hypixel/hytale/math/vector/Vector3i.getY:()I
       111: aload         13
       113: invokevirtual #282                // Method com/hypixel/hytale/math/vector/Vector3i.getZ:()I
       116: invokevirtual #218                // Method com/hypixel/hytale/server/core/universe/world/chunk/section/BlockSection.invalidateBlock:(III)V
       119: return
       120: aload         16
       122: invokevirtual #660                // Method com/hypixel/hytale/server/core/event/events/ecs/BreakBlockEvent.getTargetBlock:()Lcom/hypixel/hytale/math/vector/Vector3i;
       125: astore        13
       127: aload         12
       129: invokevirtual #661                // Method com/hypixel/hytale/server/core/universe/world/World.getChunkStore:()Lcom/hypixel/hytale/server/core/universe/world/storage/ChunkStore;
       132: invokevirtual #665                // Method com/hypixel/hytale/server/core/universe/world/storage/ChunkStore.getStore:()Lcom/hypixel/hytale/component/Store;
       135: astore        15
       137: aload         13
       139: getfield      #174                // Field com/hypixel/hytale/math/vector/Vector3i.x:I
       142: aload         13
       144: getfield      #177                // Field com/hypixel/hytale/math/vector/Vector3i.z:I
       147: invokestatic  #669                // Method com/hypixel/hytale/math/util/ChunkUtil.indexChunkFromBlock:(II)J
       150: lstore        17
       152: aload         15
       154: invokeinterface #126,  1          // InterfaceMethod com/hypixel/hytale/component/ComponentAccessor.getExternalData:()Ljava/lang/Object;
       159: checkcast     #641                // class com/hypixel/hytale/server/core/universe/world/storage/ChunkStore
       162: lload         17
       164: invokevirtual #673                // Method com/hypixel/hytale/server/core/universe/world/storage/ChunkStore.getChunkReference:(J)Lcom/hypixel/hytale/component/Ref;
       167: astore        14
       169: aload         14
       171: ifnull        182
       174: aload         14
       176: invokevirtual #677                // Method com/hypixel/hytale/component/Ref.isValid:()Z
       179: ifne          183
       182: return
       183: aload         13
       185: aload_1
       186: invokevirtual #682                // Method com/hypixel/hytale/math/vector/Vector3i.equals:(Ljava/lang/Object;)Z
       189: ifeq          201
       192: aload         12
       194: aload_0
       195: invokevirtual #683                // Method com/hypixel/hytale/server/core/universe/world/World.equals:(Ljava/lang/Object;)Z
       198: ifne          265
       201: aload         11
       203: aload         9
       205: invokestatic  #154                // Method com/hypixel/hytale/server/core/universe/world/chunk/BlockChunk.getComponentType:()Lcom/hypixel/hytale/component/ComponentType;
       208: invokeinterface #150,  3          // InterfaceMethod com/hypixel/hytale/component/ComponentAccessor.getComponent:(Lcom/hypixel/hytale/component/Ref;Lcom/hypixel/hytale/component/ComponentType;)Lcom/hypixel/hytale/component/Component;
       213: checkcast     #155                // class com/hypixel/hytale/server/core/universe/world/chunk/BlockChunk
       216: astore        16
       218: getstatic     #157                // Field $assertionsDisabled:Z
       221: ifne          237
       224: aload         16
       226: ifnonnull     237
       229: new           #161                // class java/lang/AssertionError
       232: dup
       233: invokespecial #163                // Method java/lang/AssertionError."<init>":()V
       236: athrow
       237: aload         16
       239: aload_1
       240: invokevirtual #279                // Method com/hypixel/hytale/math/vector/Vector3i.getY:()I
       243: invokevirtual #170                // Method com/hypixel/hytale/server/core/universe/world/chunk/BlockChunk.getSectionAtBlockY:(I)Lcom/hypixel/hytale/server/core/universe/world/chunk/section/BlockSection;
       246: astore        17
       248: aload         17
       250: aload_1
       251: invokevirtual #275                // Method com/hypixel/hytale/math/vector/Vector3i.getX:()I
       254: aload_1
       255: invokevirtual #279                // Method com/hypixel/hytale/math/vector/Vector3i.getY:()I
       258: aload_1
       259: invokevirtual #282                // Method com/hypixel/hytale/math/vector/Vector3i.getZ:()I
       262: invokevirtual #218                // Method com/hypixel/hytale/server/core/universe/world/chunk/section/BlockSection.invalidateBlock:(III)V
       265: aload_1
       266: invokevirtual #275                // Method com/hypixel/hytale/math/vector/Vector3i.getX:()I
       269: istore        16
       271: aload_1
       272: invokevirtual #279                // Method com/hypixel/hytale/math/vector/Vector3i.getY:()I
       275: istore        17
       277: aload_1
       278: invokevirtual #282                // Method com/hypixel/hytale/math/vector/Vector3i.getZ:()I
       281: istore        18
       283: aload         11
       285: aload         14
       287: invokestatic  #154                // Method com/hypixel/hytale/server/core/universe/world/chunk/BlockChunk.getComponentType:()Lcom/hypixel/hytale/component/ComponentType;
       290: invokeinterface #150,  3          // InterfaceMethod com/hypixel/hytale/component/ComponentAccessor.getComponent:(Lcom/hypixel/hytale/component/Ref;Lcom/hypixel/hytale/component/ComponentType;)Lcom/hypixel/hytale/component/Component;
       295: checkcast     #155                // class com/hypixel/hytale/server/core/universe/world/chunk/BlockChunk
       298: astore        19
       300: getstatic     #157                // Field $assertionsDisabled:Z
       303: ifne          319
       306: aload         19
       308: ifnonnull     319
       311: new           #161                // class java/lang/AssertionError
       314: dup
       315: invokespecial #163                // Method java/lang/AssertionError."<init>":()V
       318: athrow
       319: aload         19
       321: iload         17
       323: invokevirtual #170                // Method com/hypixel/hytale/server/core/universe/world/chunk/BlockChunk.getSectionAtBlockY:(I)Lcom/hypixel/hytale/server/core/universe/world/chunk/section/BlockSection;
       326: astore        20
       328: aload         20
       330: iload         16
       332: iload         17
       334: iload         18
       336: invokevirtual #252                // Method com/hypixel/hytale/server/core/universe/world/chunk/section/BlockSection.getFiller:(III)I
       339: istore        21
       341: aload         20
       343: iload         16
       345: iload         17
       347: iload         18
       349: invokevirtual #684                // Method com/hypixel/hytale/server/core/universe/world/chunk/section/BlockSection.get:(III)I
       352: istore        22
       354: invokestatic  #79                 // Method com/hypixel/hytale/server/core/asset/type/blocktype/config/BlockType.getAssetMap:()Lcom/hypixel/hytale/assetstore/map/BlockTypeAssetMap;
       357: iload         22
       359: invokevirtual #647                // Method com/hypixel/hytale/assetstore/map/BlockTypeAssetMap.getAsset:(I)Lcom/hypixel/hytale/assetstore/map/JsonAssetWithMap;
       362: checkcast     #8                  // class com/hypixel/hytale/server/core/asset/type/blocktype/config/BlockType
       365: astore        23
       367: aload         8
       369: aload         10
       371: invokestatic  #686                // Method com/hypixel/hytale/server/core/modules/interaction/BlockInteractionUtils.isNaturalAction:(Lcom/hypixel/hytale/component/Ref;Lcom/hypixel/hytale/component/ComponentAccessor;)Z
       374: istore        24
       376: iload         7
       378: sipush        256
       381: ior
       382: istore        7
       384: iload         24
       386: ifne          397
       389: iload         7
       391: sipush        2048
       394: ior
       395: istore        7
       397: aload         13
       399: aload         23
       401: iload         21
       403: iload         4
       405: aload         5
       407: aload         6
       409: iload         7
       411: aload         14
       413: aload         10
       415: aload         15
       417: invokestatic  #691                // Method naturallyRemoveBlock:(Lcom/hypixel/hytale/math/vector/Vector3i;Lcom/hypixel/hytale/server/core/asset/type/blocktype/config/BlockType;IILjava/lang/String;Ljava/lang/String;ILcom/hypixel/hytale/component/Ref;Lcom/hypixel/hytale/component/ComponentAccessor;Lcom/hypixel/hytale/component/ComponentAccessor;)V
       420: return

  public static void naturallyRemoveBlockByPhysics(com.hypixel.hytale.math.vector.Vector3i, com.hypixel.hytale.server.core.asset.type.blocktype.config.BlockType, int, int, com.hypixel.hytale.component.Ref<com.hypixel.hytale.server.core.universe.world.storage.ChunkStore>, com.hypixel.hytale.component.ComponentAccessor<com.hypixel.hytale.server.core.universe.world.storage.EntityStore>, com.hypixel.hytale.component.ComponentAccessor<com.hypixel.hytale.server.core.universe.world.storage.ChunkStore>);
    Code:
         0: iconst_1
         1: istore        7
         3: aconst_null
         4: astore        8
         6: aconst_null
         7: astore        9
         9: aload_1
        10: invokevirtual #7                  // Method com/hypixel/hytale/server/core/asset/type/blocktype/config/BlockType.getGathering:()Lcom/hypixel/hytale/server/core/asset/type/blocktype/config/BlockGathering;
        13: astore        10
        15: aload         10
        17: ifnull        140
        20: aload         10
        22: invokevirtual #695                // Method com/hypixel/hytale/server/core/asset/type/blocktype/config/BlockGathering.getPhysics:()Lcom/hypixel/hytale/server/core/asset/type/blocktype/config/PhysicsDropType;
        25: astore        11
        27: aload         10
        29: invokevirtual #13                 // Method com/hypixel/hytale/server/core/asset/type/blocktype/config/BlockGathering.getBreaking:()Lcom/hypixel/hytale/server/core/asset/type/blocktype/config/BlockBreakingDropType;
        32: astore        12
        34: aload         10
        36: invokevirtual #343                // Method com/hypixel/hytale/server/core/asset/type/blocktype/config/BlockGathering.getSoft:()Lcom/hypixel/hytale/server/core/asset/type/blocktype/config/SoftBlockDropType;
        39: astore        13
        41: aload         10
        43: invokevirtual #699                // Method com/hypixel/hytale/server/core/asset/type/blocktype/config/BlockGathering.getHarvest:()Lcom/hypixel/hytale/server/core/asset/type/blocktype/config/HarvestingDropType;
        46: astore        14
        48: aload         11
        50: ifnull        70
        53: aload         11
        55: invokevirtual #703                // Method com/hypixel/hytale/server/core/asset/type/blocktype/config/PhysicsDropType.getItemId:()Ljava/lang/String;
        58: astore        8
        60: aload         11
        62: invokevirtual #706                // Method com/hypixel/hytale/server/core/asset/type/blocktype/config/PhysicsDropType.getDropListId:()Ljava/lang/String;
        65: astore        9
        67: goto          140
        70: aload         12
        72: ifnull        99
        75: aload         12
        77: invokevirtual #334                // Method com/hypixel/hytale/server/core/asset/type/blocktype/config/BlockBreakingDropType.getQuantity:()I
        80: istore        7
        82: aload         12
        84: invokevirtual #337                // Method com/hypixel/hytale/server/core/asset/type/blocktype/config/BlockBreakingDropType.getItemId:()Ljava/lang/String;
        87: astore        8
        89: aload         12
        91: invokevirtual #340                // Method com/hypixel/hytale/server/core/asset/type/blocktype/config/BlockBreakingDropType.getDropListId:()Ljava/lang/String;
        94: astore        9
        96: goto          140
        99: aload         13
       101: ifnull        121
       104: aload         13
       106: invokevirtual #352                // Method com/hypixel/hytale/server/core/asset/type/blocktype/config/SoftBlockDropType.getItemId:()Ljava/lang/String;
       109: astore        8
       111: aload         13
       113: invokevirtual #353                // Method com/hypixel/hytale/server/core/asset/type/blocktype/config/SoftBlockDropType.getDropListId:()Ljava/lang/String;
       116: astore        9
       118: goto          140
       121: aload         14
       123: ifnull        140
       126: aload         14
       128: invokevirtual #707                // Method com/hypixel/hytale/server/core/asset/type/blocktype/config/HarvestingDropType.getItemId:()Ljava/lang/String;
       131: astore        8
       133: aload         14
       135: invokevirtual #710                // Method com/hypixel/hytale/server/core/asset/type/blocktype/config/HarvestingDropType.getDropListId:()Ljava/lang/String;
       138: astore        9
       140: iload_3
       141: bipush        32
       143: ior
       144: istore_3
       145: aload_0
       146: aload_1
       147: iload_2
       148: iload         7
       150: aload         8
       152: aload         9
       154: iload_3
       155: aload         4
       157: aload         5
       159: aload         6
       161: invokestatic  #691                // Method naturallyRemoveBlock:(Lcom/hypixel/hytale/math/vector/Vector3i;Lcom/hypixel/hytale/server/core/asset/type/blocktype/config/BlockType;IILjava/lang/String;Ljava/lang/String;ILcom/hypixel/hytale/component/Ref;Lcom/hypixel/hytale/component/ComponentAccessor;Lcom/hypixel/hytale/component/ComponentAccessor;)V
       164: return

  public static void naturallyRemoveBlock(com.hypixel.hytale.math.vector.Vector3i, com.hypixel.hytale.server.core.asset.type.blocktype.config.BlockType, int, int, java.lang.String, java.lang.String, int, com.hypixel.hytale.component.Ref<com.hypixel.hytale.server.core.universe.world.storage.ChunkStore>, com.hypixel.hytale.component.ComponentAccessor<com.hypixel.hytale.server.core.universe.world.storage.EntityStore>, com.hypixel.hytale.component.ComponentAccessor<com.hypixel.hytale.server.core.universe.world.storage.ChunkStore>);
    Code:
         0: aload_1
         1: ifnonnull     5
         4: return
         5: aload         9
         7: aload         7
         9: invokestatic  #144                // Method com/hypixel/hytale/server/core/universe/world/chunk/WorldChunk.getComponentType:()Lcom/hypixel/hytale/component/ComponentType;
        12: invokeinterface #150,  3          // InterfaceMethod com/hypixel/hytale/component/ComponentAccessor.getComponent:(Lcom/hypixel/hytale/component/Ref;Lcom/hypixel/hytale/component/ComponentType;)Lcom/hypixel/hytale/component/Component;
        17: checkcast     #145                // class com/hypixel/hytale/server/core/universe/world/chunk/WorldChunk
        20: astore        10
        22: getstatic     #157                // Field $assertionsDisabled:Z
        25: ifne          41
        28: aload         10
        30: ifnonnull     41
        33: new           #161                // class java/lang/AssertionError
        36: dup
        37: invokespecial #163                // Method java/lang/AssertionError."<init>":()V
        40: athrow
        41: aload         9
        43: aload         7
        45: invokestatic  #154                // Method com/hypixel/hytale/server/core/universe/world/chunk/BlockChunk.getComponentType:()Lcom/hypixel/hytale/component/ComponentType;
        48: invokeinterface #150,  3          // InterfaceMethod com/hypixel/hytale/component/ComponentAccessor.getComponent:(Lcom/hypixel/hytale/component/Ref;Lcom/hypixel/hytale/component/ComponentType;)Lcom/hypixel/hytale/component/Component;
        53: checkcast     #155                // class com/hypixel/hytale/server/core/universe/world/chunk/BlockChunk
        56: astore        11
        58: getstatic     #157                // Field $assertionsDisabled:Z
        61: ifne          77
        64: aload         11
        66: ifnonnull     77
        69: new           #161                // class java/lang/AssertionError
        72: dup
        73: invokespecial #163                // Method java/lang/AssertionError."<init>":()V
        76: athrow
        77: aload_0
        78: astore        12
        80: aload_1
        81: invokevirtual #249                // Method com/hypixel/hytale/server/core/asset/type/blocktype/config/BlockType.isUnknown:()Z
        84: ifne          218
        87: iload_2
        88: invokestatic  #255                // Method com/hypixel/hytale/server/core/util/FillerBlockUtil.unpackX:(I)I
        91: istore        13
        93: iload_2
        94: invokestatic  #261                // Method com/hypixel/hytale/server/core/util/FillerBlockUtil.unpackY:(I)I
        97: istore        14
        99: iload_2
       100: invokestatic  #264                // Method com/hypixel/hytale/server/core/util/FillerBlockUtil.unpackZ:(I)I
       103: istore        15
       105: iload         13
       107: ifne          120
       110: iload         14
       112: ifne          120
       115: iload         15
       117: ifeq          218
       120: aload         12
       122: invokevirtual #267                // Method com/hypixel/hytale/math/vector/Vector3i.clone:()Lcom/hypixel/hytale/math/vector/Vector3i;
       125: iload         13
       127: iload         14
       129: iload         15
       131: invokevirtual #271                // Method com/hypixel/hytale/math/vector/Vector3i.subtract:(III)Lcom/hypixel/hytale/math/vector/Vector3i;
       134: astore        12
       136: aload_1
       137: invokevirtual #76                 // Method com/hypixel/hytale/server/core/asset/type/blocktype/config/BlockType.getId:()Ljava/lang/String;
       140: astore        16
       142: aload         10
       144: aload         12
       146: invokevirtual #275                // Method com/hypixel/hytale/math/vector/Vector3i.getX:()I
       149: aload         12
       151: invokevirtual #279                // Method com/hypixel/hytale/math/vector/Vector3i.getY:()I
       154: aload         12
       156: invokevirtual #282                // Method com/hypixel/hytale/math/vector/Vector3i.getZ:()I
       159: invokevirtual #222                // Method com/hypixel/hytale/server/core/universe/world/chunk/WorldChunk.getBlockType:(III)Lcom/hypixel/hytale/server/core/asset/type/blocktype/config/BlockType;
       162: astore_1
       163: aload_1
       164: ifnonnull     185
       167: new           #711                // class java/lang/IllegalStateException
       170: dup
       171: aload         12
       173: invokestatic  #713                // Method java/lang/String.valueOf:(Ljava/lang/Object;)Ljava/lang/String;
       176: invokedynamic #717,  0            // InvokeDynamic #1:makeConcatWithConstants:(Ljava/lang/String;)Ljava/lang/String;
       181: invokespecial #718                // Method java/lang/IllegalStateException."<init>":(Ljava/lang/String;)V
       184: athrow
       185: aload         16
       187: aload_1
       188: invokevirtual #76                 // Method com/hypixel/hytale/server/core/asset/type/blocktype/config/BlockType.getId:()Ljava/lang/String;
       191: invokevirtual #286                // Method java/lang/String.equals:(Ljava/lang/Object;)Z
       194: ifne          218
       197: aload         10
       199: aload_0
       200: invokevirtual #275                // Method com/hypixel/hytale/math/vector/Vector3i.getX:()I
       203: aload_0
       204: invokevirtual #279                // Method com/hypixel/hytale/math/vector/Vector3i.getY:()I
       207: aload_0
       208: invokevirtual #282                // Method com/hypixel/hytale/math/vector/Vector3i.getZ:()I
       211: iload         6
       213: invokevirtual #719                // Method com/hypixel/hytale/server/core/universe/world/chunk/WorldChunk.breakBlock:(IIII)Z
       216: pop
       217: return
       218: iload         6
       220: sipush        1024
       223: iand
       224: ifne          334
       227: invokestatic  #510                // Method com/hypixel/hytale/server/core/asset/type/blocksound/config/BlockSoundSet.getAssetMap:()Lcom/hypixel/hytale/assetstore/map/IndexedLookupTableAssetMap;
       230: aload_1
       231: invokevirtual #513                // Method com/hypixel/hytale/server/core/asset/type/blocktype/config/BlockType.getBlockSoundSetIndex:()I
       234: invokevirtual #194                // Method com/hypixel/hytale/assetstore/map/IndexedLookupTableAssetMap.getAsset:(I)Lcom/hypixel/hytale/assetstore/map/JsonAssetWithMap;
       237: checkcast     #511                // class com/hypixel/hytale/server/core/asset/type/blocksound/config/BlockSoundSet
       240: astore        13
       242: aload         13
       244: ifnull        334
       247: aload         13
       249: invokevirtual #516                // Method com/hypixel/hytale/server/core/asset/type/blocksound/config/BlockSoundSet.getSoundEventIndices:()Lit/unimi/dsi/fastutil/objects/Object2IntMap;
       252: getstatic     #520                // Field com/hypixel/hytale/protocol/BlockSoundEvent.Break:Lcom/hypixel/hytale/protocol/BlockSoundEvent;
       255: iconst_0
       256: invokeinterface #528,  3          // InterfaceMethod it/unimi/dsi/fastutil/objects/Object2IntMap.getOrDefault:(Ljava/lang/Object;I)I
       261: istore        14
       263: iload         14
       265: ifeq          334
       268: aload         11
       270: aload_0
       271: invokevirtual #279                // Method com/hypixel/hytale/math/vector/Vector3i.getY:()I
       274: invokevirtual #170                // Method com/hypixel/hytale/server/core/universe/world/chunk/BlockChunk.getSectionAtBlockY:(I)Lcom/hypixel/hytale/server/core/universe/world/chunk/section/BlockSection;
       277: astore        15
       279: aload         15
       281: aload_0
       282: invokevirtual #275                // Method com/hypixel/hytale/math/vector/Vector3i.getX:()I
       285: aload_0
       286: invokevirtual #279                // Method com/hypixel/hytale/math/vector/Vector3i.getY:()I
       289: aload_0
       290: invokevirtual #282                // Method com/hypixel/hytale/math/vector/Vector3i.getZ:()I
       293: invokevirtual #180                // Method com/hypixel/hytale/server/core/universe/world/chunk/section/BlockSection.getRotationIndex:(III)I
       296: istore        16
       298: new           #236                // class com/hypixel/hytale/math/vector/Vector3d
       301: dup
       302: invokespecial #238                // Method com/hypixel/hytale/math/vector/Vector3d."<init>":()V
       305: astore        17
       307: aload_1
       308: iload         16
       310: aload         17
       312: invokevirtual #239                // Method com/hypixel/hytale/server/core/asset/type/blocktype/config/BlockType.getBlockCenter:(ILcom/hypixel/hytale/math/vector/Vector3d;)V
       315: aload         17
       317: aload_0
       318: invokevirtual #243                // Method com/hypixel/hytale/math/vector/Vector3d.add:(Lcom/hypixel/hytale/math/vector/Vector3i;)Lcom/hypixel/hytale/math/vector/Vector3d;
       321: pop
       322: iload         14
       324: getstatic     #534                // Field com/hypixel/hytale/protocol/SoundCategory.SFX:Lcom/hypixel/hytale/protocol/SoundCategory;
       327: aload         17
       329: aload         8
       331: invokestatic  #540                // Method com/hypixel/hytale/server/core/universe/world/SoundUtil.playSoundEvent3d:(ILcom/hypixel/hytale/protocol/SoundCategory;Lcom/hypixel/hytale/math/vector/Vector3d;Lcom/hypixel/hytale/component/ComponentAccessor;)V
       334: aload         12
       336: aload_1
       337: iload         6
       339: aload         7
       341: aload         9
       343: invokestatic  #720                // Method removeBlock:(Lcom/hypixel/hytale/math/vector/Vector3i;Lcom/hypixel/hytale/server/core/asset/type/blocktype/config/BlockType;ILcom/hypixel/hytale/component/Ref;Lcom/hypixel/hytale/component/ComponentAccessor;)V
       346: iload         6
       348: sipush        2048
       351: iand
       352: ifne          413
       355: iload_3
       356: ifle          413
       359: aload_0
       360: invokevirtual #724                // Method com/hypixel/hytale/math/vector/Vector3i.toVector3d:()Lcom/hypixel/hytale/math/vector/Vector3d;
       363: ldc2_w        #549                // double 0.5d
       366: dconst_0
       367: ldc2_w        #549                // double 0.5d
       370: invokevirtual #728                // Method com/hypixel/hytale/math/vector/Vector3d.add:(DDD)Lcom/hypixel/hytale/math/vector/Vector3d;
       373: astore        13
       375: aload_1
       376: iload_3
       377: aload         4
       379: aload         5
       381: invokestatic  #545                // Method getDrops:(Lcom/hypixel/hytale/server/core/asset/type/blocktype/config/BlockType;ILjava/lang/String;Ljava/lang/String;)Ljava/util/List;
       384: astore        14
       386: aload         8
       388: aload         14
       390: aload         13
       392: getstatic     #554                // Field com/hypixel/hytale/math/vector/Vector3f.ZERO:Lcom/hypixel/hytale/math/vector/Vector3f;
       395: invokestatic  #560                // Method com/hypixel/hytale/server/core/modules/entity/item/ItemComponent.generateItemDrops:(Lcom/hypixel/hytale/component/ComponentAccessor;Ljava/util/List;Lcom/hypixel/hytale/math/vector/Vector3d;Lcom/hypixel/hytale/math/vector/Vector3f;)[Lcom/hypixel/hytale/component/Holder;
       398: astore        15
       400: aload         8
       402: aload         15
       404: getstatic     #566                // Field com/hypixel/hytale/component/AddReason.SPAWN:Lcom/hypixel/hytale/component/AddReason;
       407: invokeinterface #572,  3          // InterfaceMethod com/hypixel/hytale/component/ComponentAccessor.addEntities:([Lcom/hypixel/hytale/component/Holder;Lcom/hypixel/hytale/component/AddReason;)[Lcom/hypixel/hytale/component/Ref;
       412: pop
       413: return

  public static boolean shouldPickupByInteraction(com.hypixel.hytale.server.core.asset.type.blocktype.config.BlockType);
    Code:
         0: aload_0
         1: ifnull        25
         4: aload_0
         5: invokevirtual #7                  // Method com/hypixel/hytale/server/core/asset/type/blocktype/config/BlockType.getGathering:()Lcom/hypixel/hytale/server/core/asset/type/blocktype/config/BlockGathering;
         8: ifnull        25
        11: aload_0
        12: invokevirtual #7                  // Method com/hypixel/hytale/server/core/asset/type/blocktype/config/BlockType.getGathering:()Lcom/hypixel/hytale/server/core/asset/type/blocktype/config/BlockGathering;
        15: invokevirtual #731                // Method com/hypixel/hytale/server/core/asset/type/blocktype/config/BlockGathering.isHarvestable:()Z
        18: ifeq          25
        21: iconst_1
        22: goto          26
        25: iconst_0
        26: ireturn

  public static void performPickupByInteraction(com.hypixel.hytale.component.Ref<com.hypixel.hytale.server.core.universe.world.storage.EntityStore>, com.hypixel.hytale.math.vector.Vector3i, com.hypixel.hytale.server.core.asset.type.blocktype.config.BlockType, int, com.hypixel.hytale.component.Ref<com.hypixel.hytale.server.core.universe.world.storage.ChunkStore>, com.hypixel.hytale.component.ComponentAccessor<com.hypixel.hytale.server.core.universe.world.storage.EntityStore>, com.hypixel.hytale.component.ComponentAccessor<com.hypixel.hytale.server.core.universe.world.storage.ChunkStore>);
    Code:
         0: aload         6
         2: aload         4
         4: invokestatic  #144                // Method com/hypixel/hytale/server/core/universe/world/chunk/WorldChunk.getComponentType:()Lcom/hypixel/hytale/component/ComponentType;
         7: invokeinterface #150,  3          // InterfaceMethod com/hypixel/hytale/component/ComponentAccessor.getComponent:(Lcom/hypixel/hytale/component/Ref;Lcom/hypixel/hytale/component/ComponentType;)Lcom/hypixel/hytale/component/Component;
        12: checkcast     #145                // class com/hypixel/hytale/server/core/universe/world/chunk/WorldChunk
        15: astore        7
        17: getstatic     #157                // Field $assertionsDisabled:Z
        20: ifne          36
        23: aload         7
        25: ifnonnull     36
        28: new           #161                // class java/lang/AssertionError
        31: dup
        32: invokespecial #163                // Method java/lang/AssertionError."<init>":()V
        35: athrow
        36: aload         6
        38: aload         4
        40: invokestatic  #154                // Method com/hypixel/hytale/server/core/universe/world/chunk/BlockChunk.getComponentType:()Lcom/hypixel/hytale/component/ComponentType;
        43: invokeinterface #150,  3          // InterfaceMethod com/hypixel/hytale/component/ComponentAccessor.getComponent:(Lcom/hypixel/hytale/component/Ref;Lcom/hypixel/hytale/component/ComponentType;)Lcom/hypixel/hytale/component/Component;
        48: checkcast     #155                // class com/hypixel/hytale/server/core/universe/world/chunk/BlockChunk
        51: astore        8
        53: getstatic     #157                // Field $assertionsDisabled:Z
        56: ifne          72
        59: aload         8
        61: ifnonnull     72
        64: new           #161                // class java/lang/AssertionError
        67: dup
        68: invokespecial #163                // Method java/lang/AssertionError."<init>":()V
        71: athrow
        72: aload_1
        73: astore        9
        75: aload_2
        76: invokevirtual #249                // Method com/hypixel/hytale/server/core/asset/type/blocktype/config/BlockType.isUnknown:()Z
        79: ifne          194
        82: iload_3
        83: invokestatic  #255                // Method com/hypixel/hytale/server/core/util/FillerBlockUtil.unpackX:(I)I
        86: istore        10
        88: iload_3
        89: invokestatic  #261                // Method com/hypixel/hytale/server/core/util/FillerBlockUtil.unpackY:(I)I
        92: istore        11
        94: iload_3
        95: invokestatic  #264                // Method com/hypixel/hytale/server/core/util/FillerBlockUtil.unpackZ:(I)I
        98: istore        12
       100: iload         10
       102: ifne          115
       105: iload         11
       107: ifne          115
       110: iload         12
       112: ifeq          194
       115: aload         9
       117: invokevirtual #267                // Method com/hypixel/hytale/math/vector/Vector3i.clone:()Lcom/hypixel/hytale/math/vector/Vector3i;
       120: iload         10
       122: iload         11
       124: iload         12
       126: invokevirtual #271                // Method com/hypixel/hytale/math/vector/Vector3i.subtract:(III)Lcom/hypixel/hytale/math/vector/Vector3i;
       129: astore        9
       131: aload_2
       132: invokevirtual #76                 // Method com/hypixel/hytale/server/core/asset/type/blocktype/config/BlockType.getId:()Ljava/lang/String;
       135: astore        13
       137: aload         7
       139: aload         9
       141: invokevirtual #275                // Method com/hypixel/hytale/math/vector/Vector3i.getX:()I
       144: aload         9
       146: invokevirtual #279                // Method com/hypixel/hytale/math/vector/Vector3i.getY:()I
       149: aload         9
       151: invokevirtual #282                // Method com/hypixel/hytale/math/vector/Vector3i.getZ:()I
       154: invokevirtual #222                // Method com/hypixel/hytale/server/core/universe/world/chunk/WorldChunk.getBlockType:(III)Lcom/hypixel/hytale/server/core/asset/type/blocktype/config/BlockType;
       157: astore_2
       158: aload_2
       159: ifnonnull     163
       162: return
       163: aload         13
       165: aload_2
       166: invokevirtual #76                 // Method com/hypixel/hytale/server/core/asset/type/blocktype/config/BlockType.getId:()Ljava/lang/String;
       169: invokevirtual #286                // Method java/lang/String.equals:(Ljava/lang/Object;)Z
       172: ifne          194
       175: aload         7
       177: aload_1
       178: invokevirtual #275                // Method com/hypixel/hytale/math/vector/Vector3i.getX:()I
       181: aload_1
       182: invokevirtual #279                // Method com/hypixel/hytale/math/vector/Vector3i.getY:()I
       185: aload_1
       186: invokevirtual #282                // Method com/hypixel/hytale/math/vector/Vector3i.getZ:()I
       189: invokevirtual #290                // Method com/hypixel/hytale/server/core/universe/world/chunk/WorldChunk.breakBlock:(III)Z
       192: pop
       193: return
       194: aload         8
       196: aload_1
       197: invokevirtual #279                // Method com/hypixel/hytale/math/vector/Vector3i.getY:()I
       200: invokevirtual #170                // Method com/hypixel/hytale/server/core/universe/world/chunk/BlockChunk.getSectionAtBlockY:(I)Lcom/hypixel/hytale/server/core/universe/world/chunk/section/BlockSection;
       203: astore        10
       205: new           #236                // class com/hypixel/hytale/math/vector/Vector3d
       208: dup
       209: invokespecial #238                // Method com/hypixel/hytale/math/vector/Vector3d."<init>":()V
       212: astore        11
       214: aload         10
       216: aload_1
       217: invokevirtual #275                // Method com/hypixel/hytale/math/vector/Vector3i.getX:()I
       220: aload_1
       221: invokevirtual #279                // Method com/hypixel/hytale/math/vector/Vector3i.getY:()I
       224: aload_1
       225: invokevirtual #282                // Method com/hypixel/hytale/math/vector/Vector3i.getZ:()I
       228: invokevirtual #180                // Method com/hypixel/hytale/server/core/universe/world/chunk/section/BlockSection.getRotationIndex:(III)I
       231: istore        12
       233: aload_2
       234: iload         12
       236: aload         11
       238: invokevirtual #239                // Method com/hypixel/hytale/server/core/asset/type/blocktype/config/BlockType.getBlockCenter:(ILcom/hypixel/hytale/math/vector/Vector3d;)V
       241: aload         11
       243: aload_1
       244: invokevirtual #243                // Method com/hypixel/hytale/math/vector/Vector3d.add:(Lcom/hypixel/hytale/math/vector/Vector3i;)Lcom/hypixel/hytale/math/vector/Vector3d;
       247: pop
       248: iconst_0
       249: istore        13
       251: iload         13
       253: sipush        256
       256: ior
       257: istore        13
       259: aload_0
       260: aload         5
       262: invokestatic  #686                // Method com/hypixel/hytale/server/core/modules/interaction/BlockInteractionUtils.isNaturalAction:(Lcom/hypixel/hytale/component/Ref;Lcom/hypixel/hytale/component/ComponentAccessor;)Z
       265: ifne          276
       268: iload         13
       270: sipush        2048
       273: ior
       274: istore        13
       276: aload         9
       278: aload_2
       279: iload         13
       281: aload         4
       283: aload         6
       285: invokestatic  #720                // Method removeBlock:(Lcom/hypixel/hytale/math/vector/Vector3i;Lcom/hypixel/hytale/server/core/asset/type/blocktype/config/BlockType;ILcom/hypixel/hytale/component/Ref;Lcom/hypixel/hytale/component/ComponentAccessor;)V
       288: aload_2
       289: invokevirtual #7                  // Method com/hypixel/hytale/server/core/asset/type/blocktype/config/BlockType.getGathering:()Lcom/hypixel/hytale/server/core/asset/type/blocktype/config/BlockGathering;
       292: invokevirtual #699                // Method com/hypixel/hytale/server/core/asset/type/blocktype/config/BlockGathering.getHarvest:()Lcom/hypixel/hytale/server/core/asset/type/blocktype/config/HarvestingDropType;
       295: astore        14
       297: aload         14
       299: invokevirtual #707                // Method com/hypixel/hytale/server/core/asset/type/blocktype/config/HarvestingDropType.getItemId:()Ljava/lang/String;
       302: astore        15
       304: aload         14
       306: invokevirtual #710                // Method com/hypixel/hytale/server/core/asset/type/blocktype/config/HarvestingDropType.getDropListId:()Ljava/lang/String;
       309: astore        16
       311: aload_2
       312: iconst_1
       313: aload         15
       315: aload         16
       317: invokestatic  #545                // Method getDrops:(Lcom/hypixel/hytale/server/core/asset/type/blocktype/config/BlockType;ILjava/lang/String;Ljava/lang/String;)Ljava/util/List;
       320: invokeinterface #734,  1          // InterfaceMethod java/util/List.iterator:()Ljava/util/Iterator;
       325: astore        17
       327: aload         17
       329: invokeinterface #738,  1          // InterfaceMethod java/util/Iterator.hasNext:()Z
       334: ifeq          362
       337: aload         17
       339: invokeinterface #743,  1          // InterfaceMethod java/util/Iterator.next:()Ljava/lang/Object;
       344: checkcast     #295                // class com/hypixel/hytale/server/core/inventory/ItemStack
       347: astore        18
       349: aload_0
       350: aload         18
       352: aload         11
       354: aload         5
       356: invokestatic  #746                // Method com/hypixel/hytale/server/core/entity/ItemUtils.interactivelyPickupItem:(Lcom/hypixel/hytale/component/Ref;Lcom/hypixel/hytale/server/core/inventory/ItemStack;Lcom/hypixel/hytale/math/vector/Vector3d;Lcom/hypixel/hytale/component/ComponentAccessor;)V
       359: goto          327
       362: iload         13
       364: sipush        1024
       367: iand
       368: ifne          424
       371: invokestatic  #510                // Method com/hypixel/hytale/server/core/asset/type/blocksound/config/BlockSoundSet.getAssetMap:()Lcom/hypixel/hytale/assetstore/map/IndexedLookupTableAssetMap;
       374: aload_2
       375: invokevirtual #513                // Method com/hypixel/hytale/server/core/asset/type/blocktype/config/BlockType.getBlockSoundSetIndex:()I
       378: invokevirtual #194                // Method com/hypixel/hytale/assetstore/map/IndexedLookupTableAssetMap.getAsset:(I)Lcom/hypixel/hytale/assetstore/map/JsonAssetWithMap;
       381: checkcast     #511                // class com/hypixel/hytale/server/core/asset/type/blocksound/config/BlockSoundSet
       384: astore        17
       386: aload         17
       388: ifnull        424
       391: aload         17
       393: invokevirtual #516                // Method com/hypixel/hytale/server/core/asset/type/blocksound/config/BlockSoundSet.getSoundEventIndices:()Lit/unimi/dsi/fastutil/objects/Object2IntMap;
       396: getstatic     #752                // Field com/hypixel/hytale/protocol/BlockSoundEvent.Harvest:Lcom/hypixel/hytale/protocol/BlockSoundEvent;
       399: iconst_0
       400: invokeinterface #528,  3          // InterfaceMethod it/unimi/dsi/fastutil/objects/Object2IntMap.getOrDefault:(Ljava/lang/Object;I)I
       405: istore        18
       407: iload         18
       409: ifeq          424
       412: iload         18
       414: getstatic     #534                // Field com/hypixel/hytale/protocol/SoundCategory.SFX:Lcom/hypixel/hytale/protocol/SoundCategory;
       417: aload         11
       419: aload         5
       421: invokestatic  #540                // Method com/hypixel/hytale/server/core/universe/world/SoundUtil.playSoundEvent3d:(ILcom/hypixel/hytale/protocol/SoundCategory;Lcom/hypixel/hytale/math/vector/Vector3d;Lcom/hypixel/hytale/component/ComponentAccessor;)V
       424: return

  protected static void removeBlock(com.hypixel.hytale.math.vector.Vector3i, com.hypixel.hytale.server.core.asset.type.blocktype.config.BlockType, int, com.hypixel.hytale.component.Ref<com.hypixel.hytale.server.core.universe.world.storage.ChunkStore>, com.hypixel.hytale.component.ComponentAccessor<com.hypixel.hytale.server.core.universe.world.storage.ChunkStore>);
    Code:
         0: aload         4
         2: invokeinterface #126,  1          // InterfaceMethod com/hypixel/hytale/component/ComponentAccessor.getExternalData:()Ljava/lang/Object;
         7: checkcast     #641                // class com/hypixel/hytale/server/core/universe/world/storage/ChunkStore
        10: invokevirtual #643                // Method com/hypixel/hytale/server/core/universe/world/storage/ChunkStore.getWorld:()Lcom/hypixel/hytale/server/core/universe/world/World;
        13: astore        5
        15: invokestatic  #431                // Method com/hypixel/hytale/server/core/modules/blockhealth/BlockHealthModule.get:()Lcom/hypixel/hytale/server/core/modules/blockhealth/BlockHealthModule;
        18: invokevirtual #436                // Method com/hypixel/hytale/server/core/modules/blockhealth/BlockHealthModule.getBlockHealthChunkComponentType:()Lcom/hypixel/hytale/component/ComponentType;
        21: astore        6
        23: aload         4
        25: aload_3
        26: aload         6
        28: invokeinterface #150,  3          // InterfaceMethod com/hypixel/hytale/component/ComponentAccessor.getComponent:(Lcom/hypixel/hytale/component/Ref;Lcom/hypixel/hytale/component/ComponentType;)Lcom/hypixel/hytale/component/Component;
        33: checkcast     #439                // class com/hypixel/hytale/server/core/modules/blockhealth/BlockHealthChunk
        36: astore        7
        38: getstatic     #157                // Field $assertionsDisabled:Z
        41: ifne          57
        44: aload         7
        46: ifnonnull     57
        49: new           #161                // class java/lang/AssertionError
        52: dup
        53: invokespecial #163                // Method java/lang/AssertionError."<init>":()V
        56: athrow
        57: aload         7
        59: aload         5
        61: aload_0
        62: invokevirtual #755                // Method com/hypixel/hytale/server/core/modules/blockhealth/BlockHealthChunk.removeBlock:(Lcom/hypixel/hytale/server/core/universe/world/World;Lcom/hypixel/hytale/math/vector/Vector3i;)V
        65: aload         4
        67: aload_3
        68: invokestatic  #144                // Method com/hypixel/hytale/server/core/universe/world/chunk/WorldChunk.getComponentType:()Lcom/hypixel/hytale/component/ComponentType;
        71: invokeinterface #150,  3          // InterfaceMethod com/hypixel/hytale/component/ComponentAccessor.getComponent:(Lcom/hypixel/hytale/component/Ref;Lcom/hypixel/hytale/component/ComponentType;)Lcom/hypixel/hytale/component/Component;
        76: checkcast     #145                // class com/hypixel/hytale/server/core/universe/world/chunk/WorldChunk
        79: astore        8
        81: getstatic     #157                // Field $assertionsDisabled:Z
        84: ifne          100
        87: aload         8
        89: ifnonnull     100
        92: new           #161                // class java/lang/AssertionError
        95: dup
        96: invokespecial #163                // Method java/lang/AssertionError."<init>":()V
        99: athrow
       100: aload         4
       102: aload_3
       103: invokestatic  #154                // Method com/hypixel/hytale/server/core/universe/world/chunk/BlockChunk.getComponentType:()Lcom/hypixel/hytale/component/ComponentType;
       106: invokeinterface #150,  3          // InterfaceMethod com/hypixel/hytale/component/ComponentAccessor.getComponent:(Lcom/hypixel/hytale/component/Ref;Lcom/hypixel/hytale/component/ComponentType;)Lcom/hypixel/hytale/component/Component;
       111: checkcast     #155                // class com/hypixel/hytale/server/core/universe/world/chunk/BlockChunk
       114: astore        9
       116: getstatic     #157                // Field $assertionsDisabled:Z
       119: ifne          135
       122: aload         9
       124: ifnonnull     135
       127: new           #161                // class java/lang/AssertionError
       130: dup
       131: invokespecial #163                // Method java/lang/AssertionError."<init>":()V
       134: athrow
       135: aload         8
       137: aload_0
       138: invokevirtual #275                // Method com/hypixel/hytale/math/vector/Vector3i.getX:()I
       141: aload_0
       142: invokevirtual #279                // Method com/hypixel/hytale/math/vector/Vector3i.getY:()I
       145: aload_0
       146: invokevirtual #282                // Method com/hypixel/hytale/math/vector/Vector3i.getZ:()I
       149: iload_2
       150: invokevirtual #719                // Method com/hypixel/hytale/server/core/universe/world/chunk/WorldChunk.breakBlock:(IIII)Z
       153: pop
       154: iload_2
       155: sipush        256
       158: iand
       159: ifeq          230
       162: aload         9
       164: aload_0
       165: getfield      #164                // Field com/hypixel/hytale/math/vector/Vector3i.y:I
       168: invokevirtual #170                // Method com/hypixel/hytale/server/core/universe/world/chunk/BlockChunk.getSectionAtBlockY:(I)Lcom/hypixel/hytale/server/core/universe/world/chunk/section/BlockSection;
       171: astore        10
       173: aload         10
       175: aload_0
       176: getfield      #174                // Field com/hypixel/hytale/math/vector/Vector3i.x:I
       179: aload_0
       180: getfield      #164                // Field com/hypixel/hytale/math/vector/Vector3i.y:I
       183: aload_0
       184: getfield      #177                // Field com/hypixel/hytale/math/vector/Vector3i.z:I
       187: invokevirtual #180                // Method com/hypixel/hytale/server/core/universe/world/chunk/section/BlockSection.getRotationIndex:(III)I
       190: istore        11
       192: invokestatic  #758                // Method com/hypixel/hytale/server/core/asset/type/blockhitbox/BlockBoundingBoxes.getAssetMap:()Lcom/hypixel/hytale/assetstore/map/IndexedLookupTableAssetMap;
       195: aload_1
       196: invokevirtual #761                // Method com/hypixel/hytale/server/core/asset/type/blocktype/config/BlockType.getHitboxTypeIndex:()I
       199: invokevirtual #194                // Method com/hypixel/hytale/assetstore/map/IndexedLookupTableAssetMap.getAsset:(I)Lcom/hypixel/hytale/assetstore/map/JsonAssetWithMap;
       202: checkcast     #759                // class com/hypixel/hytale/server/core/asset/type/blockhitbox/BlockBoundingBoxes
       205: astore        12
       207: aload         12
       209: ifnull        230
       212: aload         12
       214: iload         11
       216: invokevirtual #764                // Method com/hypixel/hytale/server/core/asset/type/blockhitbox/BlockBoundingBoxes.get:(I)Lcom/hypixel/hytale/server/core/asset/type/blockhitbox/BlockBoundingBoxes$RotatedVariantBoxes;
       219: aload         5
       221: aload_0
       222: invokedynamic #767,  0            // InvokeDynamic #2:accept:(Lcom/hypixel/hytale/server/core/universe/world/World;Lcom/hypixel/hytale/math/vector/Vector3i;)Lcom/hypixel/hytale/function/consumer/TriIntConsumer;
       227: invokestatic  #771                // Method com/hypixel/hytale/server/core/util/FillerBlockUtil.forEachFillerBlock:(Lcom/hypixel/hytale/server/core/asset/type/blockhitbox/BlockBoundingBoxes$RotatedVariantBoxes;Lcom/hypixel/hytale/function/consumer/TriIntConsumer;)V
       230: invokestatic  #79                 // Method com/hypixel/hytale/server/core/asset/type/blocktype/config/BlockType.getAssetMap:()Lcom/hypixel/hytale/assetstore/map/BlockTypeAssetMap;
       233: ldc_w         #775                // String Empty
       236: invokevirtual #82                 // Method com/hypixel/hytale/assetstore/map/BlockTypeAssetMap.getIndex:(Ljava/lang/Object;)I
       239: getstatic     #777                // Field com/hypixel/hytale/server/core/asset/type/blocktype/config/RotationTuple.NONE:Lcom/hypixel/hytale/server/core/asset/type/blocktype/config/RotationTuple;
       242: getstatic     #783                // Field com/hypixel/hytale/math/vector/Vector3i.ZERO:Lcom/hypixel/hytale/math/vector/Vector3i;
       245: aload_0
       246: aload         8
       248: aload         9
       250: invokestatic  #786                // Method com/hypixel/hytale/server/core/universe/world/connectedblocks/ConnectedBlocksUtil.setConnectedBlockAndNotifyNeighbors:(ILcom/hypixel/hytale/server/core/asset/type/blocktype/config/RotationTuple;Lcom/hypixel/hytale/math/vector/Vector3i;Lcom/hypixel/hytale/math/vector/Vector3i;Lcom/hypixel/hytale/server/core/universe/world/chunk/WorldChunk;Lcom/hypixel/hytale/server/core/universe/world/chunk/BlockChunk;)V
       253: return

  public static java.util.List<com.hypixel.hytale.server.core.inventory.ItemStack> getDrops(com.hypixel.hytale.server.core.asset.type.blocktype.config.BlockType, int, java.lang.String, java.lang.String);
    Code:
         0: aload_3
         1: ifnonnull     40
         4: aload_2
         5: ifnonnull     40
         8: aload_0
         9: invokevirtual #792                // Method com/hypixel/hytale/server/core/asset/type/blocktype/config/BlockType.getItem:()Lcom/hypixel/hytale/server/core/asset/type/item/config/Item;
        12: astore        4
        14: aload         4
        16: ifnonnull     23
        19: invokestatic  #793                // Method it/unimi/dsi/fastutil/objects/ObjectLists.emptyList:()Lit/unimi/dsi/fastutil/objects/ObjectList;
        22: areturn
        23: new           #295                // class com/hypixel/hytale/server/core/inventory/ItemStack
        26: dup
        27: aload         4
        29: invokevirtual #798                // Method com/hypixel/hytale/server/core/asset/type/item/config/Item.getId:()Ljava/lang/String;
        32: iload_1
        33: invokespecial #799                // Method com/hypixel/hytale/server/core/inventory/ItemStack."<init>":(Ljava/lang/String;I)V
        36: invokestatic  #802                // Method it/unimi/dsi/fastutil/objects/ObjectLists.singleton:(Ljava/lang/Object;)Lit/unimi/dsi/fastutil/objects/ObjectList;
        39: areturn
        40: new           #806                // class it/unimi/dsi/fastutil/objects/ObjectArrayList
        43: dup
        44: invokespecial #808                // Method it/unimi/dsi/fastutil/objects/ObjectArrayList."<init>":()V
        47: astore        4
        49: aload_3
        50: ifnull        99
        53: invokestatic  #809                // Method com/hypixel/hytale/server/core/modules/item/ItemModule.get:()Lcom/hypixel/hytale/server/core/modules/item/ItemModule;
        56: astore        5
        58: aload         5
        60: invokevirtual #814                // Method com/hypixel/hytale/server/core/modules/item/ItemModule.isEnabled:()Z
        63: ifeq          99
        66: iconst_0
        67: istore        6
        69: iload         6
        71: iload_1
        72: if_icmpge     99
        75: aload         5
        77: aload_3
        78: invokevirtual #817                // Method com/hypixel/hytale/server/core/modules/item/ItemModule.getRandomItemDrops:(Ljava/lang/String;)Ljava/util/List;
        81: astore        7
        83: aload         4
        85: aload         7
        87: invokeinterface #821,  2          // InterfaceMethod java/util/List.addAll:(Ljava/util/Collection;)Z
        92: pop
        93: iinc          6, 1
        96: goto          69
        99: aload_2
       100: ifnull        120
       103: aload         4
       105: new           #295                // class com/hypixel/hytale/server/core/inventory/ItemStack
       108: dup
       109: aload_2
       110: iload_1
       111: invokespecial #799                // Method com/hypixel/hytale/server/core/inventory/ItemStack."<init>":(Ljava/lang/String;I)V
       114: invokeinterface #825,  2          // InterfaceMethod java/util/List.add:(Ljava/lang/Object;)Z
       119: pop
       120: aload         4
       122: areturn

  private static void lambda$removeBlock$0(com.hypixel.hytale.server.core.universe.world.World, com.hypixel.hytale.math.vector.Vector3i, int, int, int);
    Code:
         0: aload_0
         1: aload_1
         2: invokevirtual #275                // Method com/hypixel/hytale/math/vector/Vector3i.getX:()I
         5: iload_2
         6: iadd
         7: aload_1
         8: invokevirtual #279                // Method com/hypixel/hytale/math/vector/Vector3i.getY:()I
        11: iload_3
        12: iadd
        13: aload_1
        14: invokevirtual #282                // Method com/hypixel/hytale/math/vector/Vector3i.getZ:()I
        17: iload         4
        19: iadd
        20: iconst_0
        21: invokevirtual #827                // Method com/hypixel/hytale/server/core/universe/world/World.performBlockUpdate:(IIIZ)Z
        24: pop
        25: return

  static {};
    Code:
         0: ldc           #121                // class com/hypixel/hytale/server/core/modules/interaction/BlockHarvestUtils
         2: invokevirtual #831                // Method java/lang/Class.desiredAssertionStatus:()Z
         5: ifne          12
         8: iconst_1
         9: goto          13
        12: iconst_0
        13: putstatic     #157                // Field $assertionsDisabled:Z
        16: return
}
