Compiled from "ItemPacketGenerator.java"
public class com.hypixel.hytale.server.core.modules.item.ItemPacketGenerator extends com.hypixel.hytale.server.core.asset.packet.AssetPacketGenerator<java.lang.String, com.hypixel.hytale.server.core.asset.type.item.config.Item, com.hypixel.hytale.assetstore.map.DefaultAssetMap<java.lang.String, com.hypixel.hytale.server.core.asset.type.item.config.Item>> {
  public com.hypixel.hytale.server.core.modules.item.ItemPacketGenerator();
    Code:
         0: aload_0
         1: invokespecial #1                  // Method com/hypixel/hytale/server/core/asset/packet/AssetPacketGenerator."<init>":()V
         4: return

  public com.hypixel.hytale.protocol.Packet generateInitPacket(com.hypixel.hytale.assetstore.map.DefaultAssetMap<java.lang.String, com.hypixel.hytale.server.core.asset.type.item.config.Item>, java.util.Map<java.lang.String, com.hypixel.hytale.server.core.asset.type.item.config.Item>);
    Code:
         0: new           #7                  // class com/hypixel/hytale/protocol/packets/assets/UpdateItems
         3: dup
         4: invokespecial #9                  // Method com/hypixel/hytale/protocol/packets/assets/UpdateItems."<init>":()V
         7: astore_3
         8: aload_3
         9: getstatic     #10                 // Field com/hypixel/hytale/protocol/UpdateType.Init:Lcom/hypixel/hytale/protocol/UpdateType;
        12: putfield      #16                 // Field com/hypixel/hytale/protocol/packets/assets/UpdateItems.type:Lcom/hypixel/hytale/protocol/UpdateType;
        15: aload_3
        16: new           #19                 // class it/unimi/dsi/fastutil/objects/Object2ObjectOpenHashMap
        19: dup
        20: invokespecial #21                 // Method it/unimi/dsi/fastutil/objects/Object2ObjectOpenHashMap."<init>":()V
        23: putfield      #22                 // Field com/hypixel/hytale/protocol/packets/assets/UpdateItems.items:Ljava/util/Map;
        26: aload_2
        27: invokeinterface #26,  1           // InterfaceMethod java/util/Map.entrySet:()Ljava/util/Set;
        32: invokeinterface #32,  1           // InterfaceMethod java/util/Set.iterator:()Ljava/util/Iterator;
        37: astore        4
        39: aload         4
        41: invokeinterface #38,  1           // InterfaceMethod java/util/Iterator.hasNext:()Z
        46: ifeq          97
        49: aload         4
        51: invokeinterface #44,  1           // InterfaceMethod java/util/Iterator.next:()Ljava/lang/Object;
        56: checkcast     #48                 // class java/util/Map$Entry
        59: astore        5
        61: aload_3
        62: getfield      #22                 // Field com/hypixel/hytale/protocol/packets/assets/UpdateItems.items:Ljava/util/Map;
        65: aload         5
        67: invokeinterface #50,  1           // InterfaceMethod java/util/Map$Entry.getKey:()Ljava/lang/Object;
        72: checkcast     #53                 // class java/lang/String
        75: aload         5
        77: invokeinterface #55,  1           // InterfaceMethod java/util/Map$Entry.getValue:()Ljava/lang/Object;
        82: checkcast     #58                 // class com/hypixel/hytale/server/core/asset/type/item/config/Item
        85: invokevirtual #60                 // Method com/hypixel/hytale/server/core/asset/type/item/config/Item.toPacket:()Lcom/hypixel/hytale/protocol/ItemBase;
        88: invokeinterface #64,  3           // InterfaceMethod java/util/Map.put:(Ljava/lang/Object;Ljava/lang/Object;)Ljava/lang/Object;
        93: pop
        94: goto          39
        97: aload_3
        98: iconst_1
        99: putfield      #68                 // Field com/hypixel/hytale/protocol/packets/assets/UpdateItems.updateModels:Z
       102: aload_3
       103: iconst_1
       104: putfield      #72                 // Field com/hypixel/hytale/protocol/packets/assets/UpdateItems.updateIcons:Z
       107: aload_3
       108: areturn

  public com.hypixel.hytale.protocol.Packet generateUpdatePacket(com.hypixel.hytale.assetstore.map.DefaultAssetMap<java.lang.String, com.hypixel.hytale.server.core.asset.type.item.config.Item>, java.util.Map<java.lang.String, com.hypixel.hytale.server.core.asset.type.item.config.Item>, com.hypixel.hytale.assetstore.AssetUpdateQuery);
    Code:
         0: new           #7                  // class com/hypixel/hytale/protocol/packets/assets/UpdateItems
         3: dup
         4: invokespecial #9                  // Method com/hypixel/hytale/protocol/packets/assets/UpdateItems."<init>":()V
         7: astore        4
         9: aload         4
        11: getstatic     #75                 // Field com/hypixel/hytale/protocol/UpdateType.AddOrUpdate:Lcom/hypixel/hytale/protocol/UpdateType;
        14: putfield      #16                 // Field com/hypixel/hytale/protocol/packets/assets/UpdateItems.type:Lcom/hypixel/hytale/protocol/UpdateType;
        17: aload         4
        19: new           #19                 // class it/unimi/dsi/fastutil/objects/Object2ObjectOpenHashMap
        22: dup
        23: invokespecial #21                 // Method it/unimi/dsi/fastutil/objects/Object2ObjectOpenHashMap."<init>":()V
        26: putfield      #22                 // Field com/hypixel/hytale/protocol/packets/assets/UpdateItems.items:Ljava/util/Map;
        29: aload_2
        30: invokeinterface #26,  1           // InterfaceMethod java/util/Map.entrySet:()Ljava/util/Set;
        35: invokeinterface #32,  1           // InterfaceMethod java/util/Set.iterator:()Ljava/util/Iterator;
        40: astore        5
        42: aload         5
        44: invokeinterface #38,  1           // InterfaceMethod java/util/Iterator.hasNext:()Z
        49: ifeq          101
        52: aload         5
        54: invokeinterface #44,  1           // InterfaceMethod java/util/Iterator.next:()Ljava/lang/Object;
        59: checkcast     #48                 // class java/util/Map$Entry
        62: astore        6
        64: aload         4
        66: getfield      #22                 // Field com/hypixel/hytale/protocol/packets/assets/UpdateItems.items:Ljava/util/Map;
        69: aload         6
        71: invokeinterface #50,  1           // InterfaceMethod java/util/Map$Entry.getKey:()Ljava/lang/Object;
        76: checkcast     #53                 // class java/lang/String
        79: aload         6
        81: invokeinterface #55,  1           // InterfaceMethod java/util/Map$Entry.getValue:()Ljava/lang/Object;
        86: checkcast     #58                 // class com/hypixel/hytale/server/core/asset/type/item/config/Item
        89: invokevirtual #60                 // Method com/hypixel/hytale/server/core/asset/type/item/config/Item.toPacket:()Lcom/hypixel/hytale/protocol/ItemBase;
        92: invokeinterface #64,  3           // InterfaceMethod java/util/Map.put:(Ljava/lang/Object;Ljava/lang/Object;)Ljava/lang/Object;
        97: pop
        98: goto          42
       101: aload_3
       102: invokevirtual #78                 // Method com/hypixel/hytale/assetstore/AssetUpdateQuery.getRebuildCache:()Lcom/hypixel/hytale/assetstore/AssetUpdateQuery$RebuildCache;
       105: astore        5
       107: aload         4
       109: aload         5
       111: invokevirtual #84                 // Method com/hypixel/hytale/assetstore/AssetUpdateQuery$RebuildCache.isBlockTextures:()Z
       114: ifne          125
       117: aload         5
       119: invokevirtual #89                 // Method com/hypixel/hytale/assetstore/AssetUpdateQuery$RebuildCache.isModels:()Z
       122: ifeq          129
       125: iconst_1
       126: goto          130
       129: iconst_0
       130: putfield      #68                 // Field com/hypixel/hytale/protocol/packets/assets/UpdateItems.updateModels:Z
       133: aload         4
       135: aload         5
       137: invokevirtual #92                 // Method com/hypixel/hytale/assetstore/AssetUpdateQuery$RebuildCache.isItemIcons:()Z
       140: putfield      #72                 // Field com/hypixel/hytale/protocol/packets/assets/UpdateItems.updateIcons:Z
       143: aload         4
       145: areturn

  public com.hypixel.hytale.protocol.Packet generateRemovePacket(com.hypixel.hytale.assetstore.map.DefaultAssetMap<java.lang.String, com.hypixel.hytale.server.core.asset.type.item.config.Item>, java.util.Set<java.lang.String>, com.hypixel.hytale.assetstore.AssetUpdateQuery);
    Code:
         0: new           #7                  // class com/hypixel/hytale/protocol/packets/assets/UpdateItems
         3: dup
         4: invokespecial #9                  // Method com/hypixel/hytale/protocol/packets/assets/UpdateItems."<init>":()V
         7: astore        4
         9: aload         4
        11: getstatic     #95                 // Field com/hypixel/hytale/protocol/UpdateType.Remove:Lcom/hypixel/hytale/protocol/UpdateType;
        14: putfield      #16                 // Field com/hypixel/hytale/protocol/packets/assets/UpdateItems.type:Lcom/hypixel/hytale/protocol/UpdateType;
        17: aload         4
        19: aload_2
        20: invokedynamic #98,  0             // InvokeDynamic #0:apply:()Ljava/util/function/IntFunction;
        25: invokeinterface #102,  2          // InterfaceMethod java/util/Set.toArray:(Ljava/util/function/IntFunction;)[Ljava/lang/Object;
        30: checkcast     #106                // class "[Ljava/lang/String;"
        33: putfield      #108                // Field com/hypixel/hytale/protocol/packets/assets/UpdateItems.removedItems:[Ljava/lang/String;
        36: aload_3
        37: invokevirtual #78                 // Method com/hypixel/hytale/assetstore/AssetUpdateQuery.getRebuildCache:()Lcom/hypixel/hytale/assetstore/AssetUpdateQuery$RebuildCache;
        40: astore        5
        42: aload         4
        44: aload         5
        46: invokevirtual #84                 // Method com/hypixel/hytale/assetstore/AssetUpdateQuery$RebuildCache.isBlockTextures:()Z
        49: ifne          60
        52: aload         5
        54: invokevirtual #89                 // Method com/hypixel/hytale/assetstore/AssetUpdateQuery$RebuildCache.isModels:()Z
        57: ifeq          64
        60: iconst_1
        61: goto          65
        64: iconst_0
        65: putfield      #68                 // Field com/hypixel/hytale/protocol/packets/assets/UpdateItems.updateModels:Z
        68: aload         4
        70: aload         5
        72: invokevirtual #92                 // Method com/hypixel/hytale/assetstore/AssetUpdateQuery$RebuildCache.isItemIcons:()Z
        75: putfield      #72                 // Field com/hypixel/hytale/protocol/packets/assets/UpdateItems.updateIcons:Z
        78: aload         4
        80: areturn

  public com.hypixel.hytale.protocol.Packet generateRemovePacket(com.hypixel.hytale.assetstore.AssetMap, java.util.Set, com.hypixel.hytale.assetstore.AssetUpdateQuery);
    Code:
         0: aload_0
         1: aload_1
         2: checkcast     #111                // class com/hypixel/hytale/assetstore/map/DefaultAssetMap
         5: aload_2
         6: aload_3
         7: invokevirtual #113                // Method generateRemovePacket:(Lcom/hypixel/hytale/assetstore/map/DefaultAssetMap;Ljava/util/Set;Lcom/hypixel/hytale/assetstore/AssetUpdateQuery;)Lcom/hypixel/hytale/protocol/Packet;
        10: areturn

  public com.hypixel.hytale.protocol.Packet generateUpdatePacket(com.hypixel.hytale.assetstore.AssetMap, java.util.Map, com.hypixel.hytale.assetstore.AssetUpdateQuery);
    Code:
         0: aload_0
         1: aload_1
         2: checkcast     #111                // class com/hypixel/hytale/assetstore/map/DefaultAssetMap
         5: aload_2
         6: aload_3
         7: invokevirtual #119                // Method generateUpdatePacket:(Lcom/hypixel/hytale/assetstore/map/DefaultAssetMap;Ljava/util/Map;Lcom/hypixel/hytale/assetstore/AssetUpdateQuery;)Lcom/hypixel/hytale/protocol/Packet;
        10: areturn

  public com.hypixel.hytale.protocol.Packet generateInitPacket(com.hypixel.hytale.assetstore.AssetMap, java.util.Map);
    Code:
         0: aload_0
         1: aload_1
         2: checkcast     #111                // class com/hypixel/hytale/assetstore/map/DefaultAssetMap
         5: aload_2
         6: invokevirtual #123                // Method generateInitPacket:(Lcom/hypixel/hytale/assetstore/map/DefaultAssetMap;Ljava/util/Map;)Lcom/hypixel/hytale/protocol/Packet;
         9: areturn

  private static java.lang.String[] lambda$generateRemovePacket$0(int);
    Code:
         0: iload_0
         1: anewarray     #53                 // class java/lang/String
         4: areturn
}
